Workbook

Sheet Diseño
A2: =VALUE(LEFT(C4,FIND(" - ",C4)-1)) -> 787 | B2: Diseño de Contenido Curricular
B4: Curso | C4: 787 - Sistemas Organizacionales y Gerenciales 2
B5: Periodo al que aplica | C5: Primer Semestre 2026
B8: No. | C8: Competencia | D8: Nombre de la Unidad | E8: Tema | F8: Subtema | G8: Mes | H8: Semana
B9: 1 | C9: Analiza oportunidades críticas y de gran valor en un entorno empresarial haciendo uso de matrices y arboles de decisión, así como herramientas para el análisis de datos para definir la mejor planificación y dirección empresarial | D9: Unidad 1 Exploración del mundo de los ERP (Enterprise Resource Planning) | E9: Exploración del mundo del los ERP: Planeación, Control y Dirección | F9: Definición de planeación. | G9: Enero | H9: 1
B10: 2 | C10: Analiza oportunidades críticas y de gran valor en un entorno empresarial haciendo uso de matrices y arboles de decisión, así como herramientas para el análisis de datos para definir la mejor planificación y dirección empresarial | D10: Unidad 1 Exploración del mundo de los ERP (Enterprise Resource Planning) | E10: Exploración del mundo del los ERP: Planeación, Control y Dirección | F10: Control en la gestión. | G10: Enero | H10: 1
B11: 3 | C11: Analiza oportunidades críticas y de gran valor en un entorno empresarial haciendo uso de matrices y arboles de decisión, así como herramientas para el análisis de datos para definir la mejor planificación y dirección empresarial | D11: Unidad 1 Exploración del mundo de los ERP (Enterprise Resource Planning) | E11: Exploración del mundo del los ERP: Planeación, Control y Dirección | F11: Dirección empresarial. | G11: Enero | H11: 1
B12: 4 | C12: Analiza oportunidades críticas y de gran valor en un entorno empresarial haciendo uso de matrices y arboles de decisión, así como herramientas para el análisis de datos para definir la mejor planificación y dirección empresarial | D12: Unidad 1 Exploración del mundo de los ERP (Enterprise Resource Planning) | E12: Exploración del mundo del los ERP: Planeación, Control y Dirección | F12: Relación entre planeación, control y dirección. | G12: Enero | H12: 1
B13: 5 | C13: Analiza oportunidades críticas y de gran valor en un entorno empresarial haciendo uso de matrices y arboles de decisión, así como herramientas para el análisis de datos para definir la mejor planificación y dirección empresarial | D13: Unidad 1 Exploración del mundo de los ERP (Enterprise Resource Planning) | E13: Exploración del mundo del los ERP: Planeación, Control y Dirección | F13: Módulos principales. | G13: Enero | H13: 1
B14: 6 | C14: Analiza oportunidades críticas y de gran valor en un entorno empresarial haciendo uso de matrices y arboles de decisión, así como herramientas para el análisis de datos para definir la mejor planificación y dirección empresarial | D14: Unidad 1 Exploración del mundo de los ERP (Enterprise Resource Planning) | E14: Exploración del mundo del los ERP: Planeación, Control y Dirección | F14: Base de datos centralizada. | G14: Enero | H14: 2
B15: 7 | C15: Analiza oportunidades críticas y de gran valor en un entorno empresarial haciendo uso de matrices y arboles de decisión, así como herramientas para el análisis de datos para definir la mejor planificación y dirección empresarial | D15: Unidad 1 Exploración del mundo de los ERP (Enterprise Resource Planning) | E15: Exploración del mundo del los ERP: Planeación, Control y Dirección | F15: Interfaz de usuario. | G15: Enero | H15: 2
B16: 8 | C16: Analiza oportunidades críticas y de gran valor en un entorno empresarial haciendo uso de matrices y arboles de decisión, así como herramientas para el análisis de datos para definir la mejor planificación y dirección empresarial | D16: Unidad 1 Exploración del mundo de los ERP (Enterprise Resource Planning) | E16: Exploración del mundo de los ERP: Función, beneficios de integración y tendencias | F16: Integración y ejemplos con aplicaciones | G16: Enero | H16: 2
B17: 9 | C17: Analiza oportunidades críticas y de gran valor en un entorno empresarial haciendo uso de matrices y arboles de decisión, así como herramientas para el análisis de datos para definir la mejor planificación y dirección empresarial | D17: Unidad 1 Exploración del mundo de los ERP (Enterprise Resource Planning) | E17: Exploración del mundo de los ERP: Función, beneficios de integración y tendencias | F17: Funciones de un ERP. | G17: Enero | H17: 2
B18: 10 | C18: Analiza oportunidades críticas y de gran valor en un entorno empresarial haciendo uso de matrices y arboles de decisión, así como herramientas para el análisis de datos para definir la mejor planificación y dirección empresarial | D18: Unidad 1 Exploración del mundo de los ERP (Enterprise Resource Planning) | E18: Exploración del mundo de los ERP: Función, beneficios de integración y tendencias | F18: Arquitectura de un ERP. | G18: Enero | H18: 2
B19: 11 | C19: Analiza oportunidades críticas y de gran valor en un entorno empresarial haciendo uso de matrices y arboles de decisión, así como herramientas para el análisis de datos para definir la mejor planificación y dirección empresarial | D19: Unidad 1 Exploración del mundo de los ERP (Enterprise Resource Planning) | E19: Exploración del mundo de los ERP: Función, beneficios de integración y tendencias | F19: Módulos y sus enfoques. | G19: Enero | H19: 2
B20: 12 | C20: Analiza oportunidades críticas y de gran valor en un entorno empresarial haciendo uso de matrices y arboles de decisión, así como herramientas para el análisis de datos para definir la mejor planificación y dirección empresarial | D20: Unidad 1 Exploración del mundo de los ERP (Enterprise Resource Planning) | E20: Exploración del mundo de los ERP: Función, beneficios de integración y tendencias | F20: Integración entre módulos. | G20: Enero | H20: 2
... B105: 97 | C105: Analiza el uso de herramientas de automatizacion de proceos (RPA), costes y beneficios del uso, el retorno de inversion con hojas de calculo y datos de costos de cada herramienta esto para tener una idea de como interactua el mismo y el uso de marketing para mejorar la persepcion y ventas de una organizacion | D105: Unidad 7 Marketing | E105: Técnicas y herramientas de segmentación de mercado, tipos de analisis de datos. | F105: Estudio de técnicas, medición y optimización. | G105: Abril | H105: 11

Sheet Semana Diagnostico
B2: Diseño de Contenido Curricular
B4: Curso | C4: ='Diseño'!C4 -> 787 - Sistemas Organizacionales y Gerenciales 2
B5: Semana | C5: 1
B6: Tiempo | C6: =B15+B22+B29+B41+B47+C48 -> 90
A9: 1. Bienvenida y Presentación | G9: Tiempo Aproximado | H9: =B15 -> 15
G10: No puedes excederte mas de 15 minutos
A11: Nombre y Formacion Academica | B11: Presentación formal de mi persona, experiencias academicas en el centro universitario y fuera de el
A12: Experiencia docente y profecional | B12: Pedir opiniones de docentes previos, dar y recibir expectativas del laboratorio, presentar mi experiencia profesional | K12: Estos puntos son recomendaciones de los puntos a tratar durante tu presentacion, si no usaras estos eres libre de agregar mas filas para indicar que haras. En los recuadros de la derecha colocar breve resumen de lo que planeas decir. No debes ser muy especifico seran pequeñas anotaciones que te ayudaran a recordar lo que planeaste
A13: Rol del auxiliar dentro del curso (funciones, actividades y apoyo a los estudiantes). | B13: Guiar al estudiante para que comprenda los temas establecidos en el programa, pueda aplicarlos en un entorno práctico y ejecute con éxito los proyectos del curso. Además, corresponde al tutor resolver dudas y facilitar el proceso de aprendizaje del estudiante
A14: Expectativas sobre la dinámica del curso | B14: Se espera un ambiente de respeto y comunicación activa, libre de burlas, insultos, faltas de respeto o cualquier manifestación despectiva hacia el tutor o los demás estudiantes. Asimismo, se solicita la participación activa, ya que esta permite al estudiante aclarar sus dudas de manera más efectiva
A15: Tiempo que emplearas | B15: 15
A18: 2. Evaluación de Conocimientos Previos | G18: Tiempo Aproximado | H18: =B22 -> 20
G19: No puedes excederte mas de 45 minutos
A20: Redactaras de 15 a 20 preguntas con sus respectivas respuestas , por lo que debes escoge los temas que evaluaras | B20: ¿Qué diferencia existe entre un ERP y un CRM? El ERP integra y gestiona procesos internos de la empresa (finanzas, producción, logística), mientras que el CRM se enfoca en la gestión de clientes, ventas y marketing. ¿Cuáles son tres módulos comunes en un ERP? Finanzas, inventarios y recursos humanos. ¿Cómo ayuda un CRM en la relación con los clientes? Centraliza información, mejora la atención personalizada y facilita el seguimiento de ventas. ¿Cuáles son las cuatro etapas del proceso administrativo? Planificación, organización, dirección y control. ¿Por qué la planificación es la base del proceso administrativo? Porque establece objetivos y define el rumbo de las demás etapas. ¿Cómo se aplica el control en una empresa de servicios? Comparando estándares de calidad con los resultados obtenidos para corregir desviaciones. ¿Cuál es la diferencia entre OLAP y OLTP? OLAP analiza grandes volúmenes de datos históricos para la toma de decisiones, mientras que OLTP gestiona transacciones operativas en tiempo real. ¿Qué es Business Intelligence? Es el conjunto de herramientas y procesos que convierten datos en información útil para decisiones estratégicas. ¿Qué ventaja ofrece OLAP frente a reportes planos? Permite análisis multidimensional, rápido y flexible (drill-down, slice and dice). ¿Para qué se utiliza la librería Pandas en Python? Para manipulación y análisis de datos en estructuras como DataFrames. ¿Para qué se utiliza la librería NumPy en Python? Para cálculos numéricos eficientes con arreglos y operaciones matemáticas. ¿Qué es RPA? Es la automatización de procesos repetitivos mediante robots de software que imitan tareas humanas en sistemas digitales. ¿Cuáles son dos ventajas de implementar RPA? Reduce errores y aumenta la eficiencia. ¿Cuáles son dos desventajas de implementar RPA? Alto costo inicial y dependencia tecnológica. ¿Qué proceso repetitivo puede automatizarse con RPA? La generación de facturas y la carga de datos en sistemas. | K20: En los recuadors de la derecha deberas colocar las preguntas que planeas realizar con sus respectivas respuestas. En el segundo recuadro deberas colocar un breve resumne de lo que tines planificado para la parte practica del curso previo al que estas impartiendo.
A21: Redactaras una parte practica | B21: Preguntas sobre herramientas y procesos como: ELT, analisis de datos e interpretacion de los mismo, utilización de herramientas como BI, RPA, CRM, ERP, DMZ
A22: Tiempo que emplearas | B22: 20
A25: 3. Presentación de los Estudiantes | G25: Tiempo Aproximado | H25: =B29 -> 20
G26: No puedes excederte mas de 30 minutos
A27: Seleccion al Azar de 5 Estudiantes | B27: Solicitud voluntaria para participación | K27: En el primer recuadro colocaras la metodollogia que adoptaras para la eleccion de los estudiantes. En el segundo recuadro colocaras la redaccion de las preguntas que comprendan los siguientes puntos respecto al estudiante: Nombre. Intereses y expectativas sobre el curso. Experiencia previa relacionada con el curso (si aplica). Un dato curioso sobre sí mismo. Consideras que la prueba de conociminetos previos esta acorde al conocimiento que se te brindo en su momento Que tan comodo se sintio con la prueba anterior.
A28: Preguntas que responderan los estudiantes afortunados | B28: Preguntas mal contestadas, se le pedirá opinion del concepto de otros temas
A29: Tiempo que emplearas | B29: 20
A32: 4. Senso de Horarios de Calificación | G32: Tiempo Aproximado | H32: =B36 -> 20
A33: Deberas estar recordando que deben contestar el formulario asi mismo dejar el link fijado en la llamada | G33: Esta actividad quedara abierta hasta el fin de la clase. pero emplearas 5 min especificos para la actividad
A34: Link de google forms donde este el cuestionario | B34: Generar el link unos días antes | K34: Esta actividad te ayudara a realizar un senso de posibles horarios de calificacion y que tus estudiantes esten enterados y puedan preveer los dias de calificacion y asi mismo el horario. Deberas colocar en los reacuadros de la derecha link de Google form libre para correos intitucionales, esto para garantizar una sola respuesta por estudiante. TAmbien deberas colocar los posibles horarios y dias que tentativamente tendrias disponibles. para colocarlos en el google form.
A35: Dias y posibles Horarios de calificacion | B35: Fines de semana de 8AM a 4PM
A36: Tiempo que emplearas | B36: 20
A39: 4. Mostrar Programa del Curso | G39: Tiempo Aproximado | H39: =B41 -> 20
G40: No puedes excederte mas de 30 minutos
A41: Tiempo que emplearas | B41: 20
A44: 2. Evaluación de Conocimientos del Curso Actual | G44: Tiempo Aproximado | H44: =B47 -> 15
G45: No puedes excederte mas de 15 minutos
A46: Redactaras 20 preguntas con sus respectivas respuestas | B46: El BPO (Business Process Outsourcing) consiste en delegar procesos internos de la empresa a un tercero especializado. Verdadero El marketing digital se limita únicamente a redes sociales. Falso El ROI (Return on Investment) mide la rentabilidad de una inversión en función de lo que se gana respecto a lo que se invierte. Verdadero El BPO siempre implica reducción de costos, sin importar el tipo de proceso externalizado. Falso Una campaña de marketing digital puede evaluarse midiendo su ROI. Verdadero ¿Cuáles son las cuatro etapas del proceso administrativo? Planificación, organización, dirección y control. ¿Qué implica la etapa de planificación? Definir objetivos, estrategias y recursos necesarios. ¿Qué se busca con la organización en el proceso administrativo? Estructurar recursos y asignar responsabilidades. ¿Qué papel cumple la dirección en el proceso administrativo? Motivar, coordinar y guiar a las personas hacia los objetivos. ¿Qué función tiene el control? Comparar resultados con lo planificado y corregir desviaciones. ¿Qué es Code Vibe? Es una metodología o enfoque que fomenta la colaboración, creatividad y productividad en equipos de desarrollo de software. ¿Por qué es importante Code Vibe en proyectos de TI? Porque mejora la comunicación y reduce errores en la construcción de soluciones. ¿Qué es la inteligencia artificial generativa? Es un tipo de IA que crea contenido nuevo (texto, imágenes, audio, código) a partir de patrones aprendidos. Menciona un ejemplo de aplicación de IA generativa. ChatGPT para generar texto o MidJourney para generar imágenes. ¿Qué diferencia existe entre análisis e interpretación? El análisis descompone la información en partes, mientras que la interpretación da sentido y conclusiones a esos datos. ¿Por qué es importante la interpretación después del análisis? Porque transforma los datos en conocimiento útil para la toma de decisiones. ¿Qué diferencia existe entre análisis e interpretación? El análisis descompone la información en partes, mientras que la interpretación da sentido y conclusiones a esos datos. ¿Por qué es importante la interpretación después del análisis? Porque transforma los datos en conocimiento útil para la toma de decisiones. ¿Qué es la toma de decisiones en administración? Es el proceso de elegir entre varias alternativas para resolver un problema o aprovechar una oportunidad. ¿Qué factores influyen en una buena toma de decisiones? Información precisa, análisis adecuado y consideración de riesgos y beneficios.
A47: Tiempo que emplearas | B47: 15

Sheet S.2
B2: Diseño de la Sesión de Laboratorio
B4: Curso | C4: ='Diseño'!C4 -> 787 - Sistemas Organizacionales y Gerenciales 2
B5: Semana | C5: 2
B6: Tiempo | C6: =H10+H21+H47+H71 -> 100
B7: Ponderación | C7: =B52+B63 -> 0
B8: Validación de Tiempo | C8: =IF(H47<=0, "❌ ERROR: La Actividad 1 debe tener un tiempo mayor a 0.", IF(H21>60, "❌ ERROR: El 'Área de Conocimiento' no puede exceder los 60 min.", IF((H71+H21+H10+H47)<100, "❌ ERROR: El tiempo total debe ser de al menos 100 min.", "✅ VALIDACIÓN CORRECTA"))) -> ✅ VALIDACIÓN CORRECTA
A10: 1. Área Actitudinal (Saber Ser) | G10: Tiempo Aproximado | H10: 5
G11: Tiene que estar en un rango de 3 a 5 minutos
A12: Nombre del Valor | B12: Respeto
A13: Tiempo Aproximado
A14: Descripcion
A15: Reconocer y valorar las opiniones, ideas y aportes de los demás, manteniendo un ambiente cordial y constructivo.
A17: Como se relaciona con los conocimientos de la sesion y se aplicaria
A18: En las sesiones sobre ERP, CRM y toma de decisiones, el respeto se refleja en la escucha activa hacia el tutor y compañeros, lo que favorece la comprensión de los conceptos y permite un trabajo colaborativo más efectivo en el análisis de casos y resolución de problemas.
A21: 2. Área Conocimiento (Saber) | G21: Tiempo Aproximado | H21: =D42+D43+D44+D45 -> 60
G22: No puede exceder los 60 minutos
A23: Competencia a desarrollar | B23: Analiza oportunidades críticas y de gran valor en un entorno empresarial haciendo uso de matrices y arboles de decisión, así como herramientas para el análisis de datos para definir la mejor planificación y dirección empresarial
A24: Competencia a desarrollar | B24: Evalúa la efectividad de procesos administrativos aplicando el ciclo del proceso administrativo para identificar áreas de mejora en la gestión organizacional y proponer acciones correctivas
A26: 2.1 Contenido
A27: No. | B27: Unidad | D27: Tema | F27: Sub Tema
A28: 1 | B28: =IFERROR(__xludf.DUMMYFUNCTION("FILTER('Diseño'!D:D,'Diseño'!H:H=$C$5)"),"Unidad 1 Exploración del mundo de los ERP (Enterprise Resource Planning)") -> Unidad 1 Exploración del mundo de los ERP (Enterprise Resource Planning) | D28: =IFERROR(__xludf.DUMMYFUNCTION("FILTER('Diseño'!E:E,'Diseño'!H:H=$C$5)"),"Exploración del mundo del los ERP: Planeación, Control y Dirección") -> Exploración del mundo del los ERP: Planeación, Control y Dirección | F28: =IFERROR(__xludf.DUMMYFUNCTION("FILTER('Diseño'!F:F,'Diseño'!H:H=$C$5)"),"Base de datos centralizada.") -> Base de datos centralizada.
A29: 2 | B29: =IFERROR(__xludf.DUMMYFUNCTION("""COMPUTED_VALUE"""),"Unidad 1 Exploración del mundo de los ERP (Enterprise Resource Planning)") -> Unidad 1 Exploración del mundo de los ERP (Enterprise Resource Planning) | D29: =IFERROR(__xludf.DUMMYFUNCTION("""COMPUTED_VALUE"""),"Exploración del mundo del los ERP: Planeación, Control y Dirección") -> Exploración del mundo del los ERP: Planeación, Control y Dirección | F29: =IFERROR(__xludf.DUMMYFUNCTION("""COMPUTED_VALUE"""),"Interfaz de usuario.") -> Interfaz de usuario.
A30: 3 | B30: =IFERROR(__xludf.DUMMYFUNCTION("""COMPUTED_VALUE"""),"Unidad 1 Exploración del mundo de los ERP (Enterprise Resource Planning)") -> Unidad 1 Exploración del mundo de los ERP (Enterprise Resource Planning) | D30: =IFERROR(__xludf.DUMMYFUNCTION("""COMPUTED_VALUE"""),"Exploración del mundo de los ERP: Función, beneficios de integración y tendencias") -> Exploración del mundo de los ERP: Función, beneficios de integración y tendencias | F30: =IFERROR(__xludf.DUMMYFUNCTION("""COMPUTED_VALUE"""),"Integración y ejemplos con aplicaciones") -> Integración y ejemplos con aplicaciones
A31: 4 | B31: =IFERROR(__xludf.DUMMYFUNCTION("""COMPUTED_VALUE"""),"Unidad 1 Exploración del mundo de los ERP (Enterprise Resource Planning)") -> Unidad 1 Exploración del mundo de los ERP (Enterprise Resource Planning) | D31: =IFERROR(__xludf.DUMMYFUNCTION("""COMPUTED_VALUE"""),"Exploración del mundo de los ERP: Función, beneficios de integración y tendencias") -> Exploración del mundo de los ERP: Función, beneficios de integración y tendencias | F31: =IFERROR(__xludf.DUMMYFUNCTION("""COMPUTED_VALUE"""),"Funciones de un ERP.") -> Funciones de un ERP.
A32: 5 | B32: =IFERROR(__xludf.DUMMYFUNCTION("""COMPUTED_VALUE"""),"Unidad 1 Exploración del mundo de los ERP (Enterprise Resource Planning)") -> Unidad 1 Exploración del mundo de los ERP (Enterprise Resource Planning) | D32: =IFERROR(__xludf.DUMMYFUNCTION("""COMPUTED_VALUE"""),"Exploración del mundo de los ERP: Función, beneficios de integración y tendencias") -> Exploración del mundo de los ERP: Función, beneficios de integración y tendencias | F32: =IFERROR(__xludf.DUMMYFUNCTION("""COMPUTED_VALUE"""),"Arquitectura de un ERP.") -> Arquitectura de un ERP.
A33: 6 | B33: =IFERROR(__xludf.DUMMYFUNCTION("""COMPUTED_VALUE"""),"Unidad 1 Exploración del mundo de los ERP (Enterprise Resource Planning)") -> Unidad 1 Exploración del mundo de los ERP (Enterprise Resource Planning) | D33: =IFERROR(__xludf.DUMMYFUNCTION("""COMPUTED_VALUE"""),"Exploración del mundo de los ERP: Función, beneficios de integración y tendencias") -> Exploración del mundo de los ERP: Función, beneficios de integración y tendencias | F33: =IFERROR(__xludf.DUMMYFUNCTION("""COMPUTED_VALUE"""),"Módulos y sus enfoques.") -> Módulos y sus enfoques.
A34: 7 | B34: =IFERROR(__xludf.DUMMYFUNCTION("""COMPUTED_VALUE"""),"Unidad 1 Exploración del mundo de los ERP (Enterprise Resource Planning)") -> Unidad 1 Exploración del mundo de los ERP (Enterprise Resource Planning) | D34: =IFERROR(__xludf.DUMMYFUNCTION("""COMPUTED_VALUE"""),"Exploración del mundo de los ERP: Función, beneficios de integración y tendencias") -> Exploración del mundo de los ERP: Función, beneficios de integración y tendencias | F34: =IFERROR(__xludf.DUMMYFUNCTION("""COMPUTED_VALUE"""),"Integración entre módulos.") -> Integración entre módulos.
B35: =IFERROR(__xludf.DUMMYFUNCTION("""COMPUTED_VALUE"""),"Unidad 1 Exploración del mundo de los ERP (Enterprise Resource Planning)") -> Unidad 1 Exploración del mundo de los ERP (Enterprise Resource Planning) | D35: =IFERROR(__xludf.DUMMYFUNCTION("""COMPUTED_VALUE"""),"Exploración del mundo de los ERP: Función, beneficios de integración y tendencias") -> Exploración del mundo de los ERP: Función, beneficios de integración y tendencias | F35: =IFERROR(__xludf.DUMMYFUNCTION("""COMPUTED_VALUE"""),"Ejemplos de ERP's especializados para cierto sector empresarial.") -> Ejemplos de ERP's especializados para cierto sector empresarial.
B36: =IFERROR(__xludf.DUMMYFUNCTION("""COMPUTED_VALUE"""),"Unidad 1 Exploración del mundo de los ERP (Enterprise Resource Planning)") -> Unidad 1 Exploración del mundo de los ERP (Enterprise Resource Planning) | D36: =IFERROR(__xludf.DUMMYFUNCTION("""COMPUTED_VALUE"""),"Exploración del mundo de los ERP: Función, beneficios de integración y tendencias") -> Exploración del mundo de los ERP: Función, beneficios de integración y tendencias | F36: =IFERROR(__xludf.DUMMYFUNCTION("""COMPUTED_VALUE"""),"Ejemplos de éxito.") -> Ejemplos de éxito.
B37: =IFERROR(__xludf.DUMMYFUNCTION("""COMPUTED_VALUE"""),"Unidad 2 Recursos y toma de decisiones basadas en tecnologías.") -> Unidad 2 Recursos y toma de decisiones basadas en tecnologías. | D37: =IFERROR(__xludf.DUMMYFUNCTION("""COMPUTED_VALUE"""),"Recursos y Toma de decisiones basadas en tecnologías: Introducción a conceptos básicos") -> Recursos y Toma de decisiones basadas en tecnologías: Introducción a conceptos básicos | F37: =IFERROR(__xludf.DUMMYFUNCTION("""COMPUTED_VALUE"""),"Definición y objetivos clave del CRM.") -> Definición y objetivos clave del CRM.
B38: =IFERROR(__xludf.DUMMYFUNCTION("""COMPUTED_VALUE"""),"Unidad 2 Recursos y toma de decisiones basadas en tecnologías.") -> Unidad 2 Recursos y toma de decisiones basadas en tecnologías. | D38: =IFERROR(__xludf.DUMMYFUNCTION("""COMPUTED_VALUE"""),"Recursos y Toma de decisiones basadas en tecnologías: Introducción a conceptos básicos") -> Recursos y Toma de decisiones basadas en tecnologías: Introducción a conceptos básicos | F38: =IFERROR(__xludf.DUMMYFUNCTION("""COMPUTED_VALUE"""),"Componentes de un sistemas CRM.") -> Componentes de un sistemas CRM.
A39: 2.2 Recursos Educativos
A41: Tipo de Recurso a utilizar | B41: Tipo | C41: Rango Aproximando | D41: Tiempo Aproximado
A42: Presentacion | B42: Obligatorio | D42: 35
A43: Video | B43: Obligatorio | C43: 3 a 6 minutos | D43: 15
A44: Lectura | B44: Optativo
A45: Ejercicio Demostrativo | B45: Obligatorio | D45: 10
A47: 3. Área de Habilidades (Saber Hacer) | G47: Tiempo Aproximado | H47: =B53+B64 -> 30
G48: Tiene que estar en un rango de 30 a 50 minutos
A49: Actividad 1 (Obligatoria)
A50: Competencia que predomina en la actividad | B50: Evalúa la efectividad de procesos administrativos aplicando el ciclo del proceso administrativo para identificar áreas de mejora en la gestión organizacional y proponer acciones correctivas
A51: Tipo de Actividad | B51: Analisis
A52: Ponderación | B52: 0
A53: Tiempo Aproximado | B53: 30
A54: Coloca el tiempo que usar en la actividad, un tiempo sugerido 30 minutos
A55: Descripcion de la Actividad
A56: Ejercicio real donde tienen que obtener las tareas y separarlas en las 4 etapas del proceso administrativo
A60: Actividad 2 (Optativa puedes hacerla si lo consideras apropiado)
A61: Competencia que predomina en la actividad
A62: Tipo de Actividad
A63: Ponderación
A64: Tiempo Aproximado
A65: Coloca el tiempo que usar en la actividad, un tiempo sugerido 20 minutos
A66: Descripcion de la Actividad
A71: 3. Cierre | G71: Tiempo Aproximado | H71: 5
G72: Tiene que estar en un rango de 10 a 15 minutos
A73: Tiempo Aproximado | B73: 5
A74: Asignacion de Actividades
A75: Resolver dudas sobre los temas vistos
A77: Resuelve alguna duda, asigna las actividades que deben realizar, dudas de proyectos, etc

Sheet S.3
B2: Diseño de la Sesión de Laboratorio
B4: Curso | C4: ='Diseño'!C4 -> 787 - Sistemas Organizacionales y Gerenciales 2
B5: Semana | C5: 3
B6: Tiempo | C6: =H10+H21+H49+H73 -> 100
B7: Ponderación | C7: =B54+B65 -> 0
B8: Validación de Tiempo | C8: =IF(H49<=0, "❌ ERROR: La Actividad 1 debe tener un tiempo mayor a 0.", IF(H21>60, "❌ ERROR: El 'Área de Conocimiento' no puede exceder los 60 min.", IF((H10+H21+H49+H73)<100, "❌ ERROR: El tiempo total debe ser de al menos 100 min.", "✅ VALIDACIÓN CORRECTA"))) -> ✅ VALIDACIÓN CORRECTA
A10: 1. Área Actitudinal (Saber Ser) | G10: Tiempo Aproximado | H10: =B13 -> 5
G11: Tiene que estar en un rango de 3 a 5 minutos
A12: Nombre del Valor | B12: Responsabilidad
A13: Tiempo Aproximado | B13: 5
A14: Descripcion
A15: Cumplir con las tareas y compromisos asignados de manera puntual y con calidad.
A17: Como se relaciona con los conocimientos de la sesion y se aplicaria
A18: En el estudio de tipos de CRM y su implementación, la responsabilidad se refleja en el uso adecuado de la información del cliente y en el cumplimiento de los procesos para mantener relaciones confiables.
A21: 2. Área Conocimiento (Saber) | G21: Tiempo Aproximado | H21: =D44+D45+D46+D47 -> 60
G22: No puede exceder los 60 minutos
A23: Competencia a desarrollar | B23: Evalúa la efectividad de procesos administrativos aplicando el ciclo del proceso administrativo para identificar áreas de mejora en la gestión organizacional y proponer acciones correctivas
A24: Competencia a desarrollar | B24: Crea propuestas de solución innovadoras utilizando metodologías de diseño estratégico en escenarios empresariales simulados de alta complejidad
A26: 2.1 Contenido
A27: No. | B27: Unidad | D27: Tema | F27: Sub Tema
A28: 1 | B28: =IFERROR(__xludf.DUMMYFUNCTION("FILTER('Diseño'!D:D,'Diseño'!H:H=$C$5)"),"Unidad 2 Recursos y toma de decisiones basadas en tecnologías.") -> Unidad 2 Recursos y toma de decisiones basadas en tecnologías. | D28: =IFERROR(__xludf.DUMMYFUNCTION("FILTER('Diseño'!E:E,'Diseño'!H:H=$C$5)"),"Recursos y Toma de decisiones basadas en tecnologías: Introducción a conceptos básicos") -> Recursos y Toma de decisiones basadas en tecnologías: Introducción a conceptos básicos | F28: =IFERROR(__xludf.DUMMYFUNCTION("FILTER('Diseño'!F:F,'Diseño'!H:H=$C$5)"),"Tipos de CRM's.") -> Tipos de CRM's.
A29: 2 | B29: =IFERROR(__xludf.DUMMYFUNCTION("""COMPUTED_VALUE"""),"Unidad 2 Recursos y toma de decisiones basadas en tecnologías.") -> Unidad 2 Recursos y toma de decisiones basadas en tecnologías. | D29: =IFERROR(__xludf.DUMMYFUNCTION("""COMPUTED_VALUE"""),"Recursos y Toma de decisiones basadas en tecnologías: Introducción a conceptos básicos") -> Recursos y Toma de decisiones basadas en tecnologías: Introducción a conceptos básicos | F29: =IFERROR(__xludf.DUMMYFUNCTION("""COMPUTED_VALUE"""),"Beneficios de un CRM e implementación.") -> Beneficios de un CRM e implementación.
A30: 3 | B30: =IFERROR(__xludf.DUMMYFUNCTION("""COMPUTED_VALUE"""),"Unidad 2 Recursos y toma de decisiones basadas en tecnologías.") -> Unidad 2 Recursos y toma de decisiones basadas en tecnologías. | D30: =IFERROR(__xludf.DUMMYFUNCTION("""COMPUTED_VALUE"""),"Recursos y Toma de decisiones basadas en tecnologías: Introducción a conceptos básicos") -> Recursos y Toma de decisiones basadas en tecnologías: Introducción a conceptos básicos | F30: =IFERROR(__xludf.DUMMYFUNCTION("""COMPUTED_VALUE"""),"Arquitectura y modularidad de un sistema CRM.") -> Arquitectura y modularidad de un sistema CRM.
A31: 4 | B31: =IFERROR(__xludf.DUMMYFUNCTION("""COMPUTED_VALUE"""),"Unidad 2 Recursos y toma de decisiones basadas en tecnologías.") -> Unidad 2 Recursos y toma de decisiones basadas en tecnologías. | D31: =IFERROR(__xludf.DUMMYFUNCTION("""COMPUTED_VALUE"""),"Recursos y Toma de decisiones basadas en tecnologías: Introducción a conceptos básicos") -> Recursos y Toma de decisiones basadas en tecnologías: Introducción a conceptos básicos | F31: =IFERROR(__xludf.DUMMYFUNCTION("""COMPUTED_VALUE"""),"Automatización e integración ERP y CRM.") -> Automatización e integración ERP y CRM.
A32: 5 | B32: =IFERROR(__xludf.DUMMYFUNCTION("""COMPUTED_VALUE"""),"Unidad 2 Recursos y toma de decisiones basadas en tecnologías.") -> Unidad 2 Recursos y toma de decisiones basadas en tecnologías. | D32: =IFERROR(__xludf.DUMMYFUNCTION("""COMPUTED_VALUE"""),"Recursos y Toma de decisiones basadas en tecnologías: Introducción a conceptos básicos") -> Recursos y Toma de decisiones basadas en tecnologías: Introducción a conceptos básicos | F32: =IFERROR(__xludf.DUMMYFUNCTION("""COMPUTED_VALUE"""),"Casos de éxito y empresas especializadas.") -> Casos de éxito y empresas especializadas.
A33: 6 | B33: =IFERROR(__xludf.DUMMYFUNCTION("""COMPUTED_VALUE"""),"Unidad 2 Recursos y toma de decisiones basadas en tecnologías.") -> Unidad 2 Recursos y toma de decisiones basadas en tecnologías. | D33: =IFERROR(__xludf.DUMMYFUNCTION("""COMPUTED_VALUE"""),"Recursos y Toma de decisiones basadas en tecnologías: Automatización, personalización y analisis.") -> Recursos y Toma de decisiones basadas en tecnologías: Automatización, personalización y analisis. | F33: =IFERROR(__xludf.DUMMYFUNCTION("""COMPUTED_VALUE"""),"Impacto en la productividad empresarial.") -> Impacto en la productividad empresarial.
A34: 7 | B34: =IFERROR(__xludf.DUMMYFUNCTION("""COMPUTED_VALUE"""),"Unidad 2 Recursos y toma de decisiones basadas en tecnologías.") -> Unidad 2 Recursos y toma de decisiones basadas en tecnologías. | D34: =IFERROR(__xludf.DUMMYFUNCTION("""COMPUTED_VALUE"""),"Recursos y Toma de decisiones basadas en tecnologías: Automatización, personalización y analisis.") -> Recursos y Toma de decisiones basadas en tecnologías: Automatización, personalización y analisis. | F34: =IFERROR(__xludf.DUMMYFUNCTION("""COMPUTED_VALUE"""),"Definiciones y tipos de analisis.") -> Definiciones y tipos de analisis.
B35: =IFERROR(__xludf.DUMMYFUNCTION("""COMPUTED_VALUE"""),"Unidad 2 Recursos y toma de decisiones basadas en tecnologías.") -> Unidad 2 Recursos y toma de decisiones basadas en tecnologías. | D35: =IFERROR(__xludf.DUMMYFUNCTION("""COMPUTED_VALUE"""),"Recursos y Toma de decisiones basadas en tecnologías: Automatización, personalización y analisis.") -> Recursos y Toma de decisiones basadas en tecnologías: Automatización, personalización y analisis. | F35: =IFERROR(__xludf.DUMMYFUNCTION("""COMPUTED_VALUE"""),"Técnicas utilizadas, modelos estadísticos.") -> Técnicas utilizadas, modelos estadísticos.
B36: =IFERROR(__xludf.DUMMYFUNCTION("""COMPUTED_VALUE"""),"Unidad 2 Recursos y toma de decisiones basadas en tecnologías.") -> Unidad 2 Recursos y toma de decisiones basadas en tecnologías. | D36: =IFERROR(__xludf.DUMMYFUNCTION("""COMPUTED_VALUE"""),"Recursos y Toma de decisiones basadas en tecnologías: Automatización, personalización y analisis.") -> Recursos y Toma de decisiones basadas en tecnologías: Automatización, personalización y analisis. | F36: =IFERROR(__xludf.DUMMYFUNCTION("""COMPUTED_VALUE"""),"Desafios y técnicas de integración.") -> Desafios y técnicas de integración.
B37: =IFERROR(__xludf.DUMMYFUNCTION("""COMPUTED_VALUE"""),"Unidad 2 Recursos y toma de decisiones basadas en tecnologías.") -> Unidad 2 Recursos y toma de decisiones basadas en tecnologías. | D37: =IFERROR(__xludf.DUMMYFUNCTION("""COMPUTED_VALUE"""),"Recursos y Toma de decisiones basadas en tecnologías: Automatización, personalización y analisis.") -> Recursos y Toma de decisiones basadas en tecnologías: Automatización, personalización y analisis. | F37: =IFERROR(__xludf.DUMMYFUNCTION("""COMPUTED_VALUE"""),"Importancia UIX y personalización.") -> Importancia UIX y personalización.
B38: =IFERROR(__xludf.DUMMYFUNCTION("""COMPUTED_VALUE"""),"Unidad 2 Recursos y toma de decisiones basadas en tecnologías.") -> Unidad 2 Recursos y toma de decisiones basadas en tecnologías. | D38: =IFERROR(__xludf.DUMMYFUNCTION("""COMPUTED_VALUE"""),"Recursos y Toma de decisiones basadas en tecnologías: Automatización, personalización y analisis.") -> Recursos y Toma de decisiones basadas en tecnologías: Automatización, personalización y analisis. | F38: =IFERROR(__xludf.DUMMYFUNCTION("""COMPUTED_VALUE"""),"Nuevas tendencias e integraciones.") -> Nuevas tendencias e integraciones.
B39: =IFERROR(__xludf.DUMMYFUNCTION("""COMPUTED_VALUE"""),"Unidad 2 Recursos y toma de decisiones basadas en tecnologías.") -> Unidad 2 Recursos y toma de decisiones basadas en tecnologías. | D39: =IFERROR(__xludf.DUMMYFUNCTION("""COMPUTED_VALUE"""),"Recursos y Toma de decisiones basadas en tecnologías: Automatización, personalización y analisis.") -> Recursos y Toma de decisiones basadas en tecnologías: Automatización, personalización y analisis. | F39: =IFERROR(__xludf.DUMMYFUNCTION("""COMPUTED_VALUE"""),"Ejemplos de éxito.") -> Ejemplos de éxito.
A41: 2.2 Recursos Educativos
A43: Tipo de Recurso a utilizar | B43: Tipo | C43: Rango Aproximando | D43: Tiempo Aproximado
A44: Presentacion | B44: Obligatorio | D44: 20
A45: Video | B45: Obligatorio | C45: 3 a 6 minutos | D45: 10
A46: Lectura | B46: Optativo | D46: 10
A47: Ejercicio Demostrativo | B47: Obligatorio | D47: 20
A49: 3. Área de Habilidades (Saber Hacer) | G49: Tiempo Aproximado | H49: =B55+B66 -> 30
G50: Tiene que estar en un rango de 30 a 50 minutos
A51: Actividad 1 (Obligatoria)
A52: Competencia que predomina en la actividad | B52: Crea propuestas de solución innovadoras utilizando metodologías de diseño estratégico en escenarios empresariales simulados de alta complejidad
A53: Tipo de Actividad | B53: Analisis
A54: Ponderación | B54: 0
A55: Tiempo Aproximado | B55: 30
A56: Coloca el tiempo que usar en la actividad, un tiempo sugerido 30 minutos
A57: Descripcion de la Actividad
A58: Exploracion de odoo y registro de al menos 1 producto, 1 proveedor, 1 cliente y 1 venta
A62: Actividad 2 (Optativa puedes hacerla si lo consideras apropiado)
A63: Competencia que predomina en la actividad
A64: Tipo de Actividad
A65: Ponderación
A66: Tiempo Aproximado
A67: Coloca el tiempo que usar en la actividad, un tiempo sugerido 20 minutos
A68: Descripcion de la Actividad
A73: 3. Cierre | G73: Tiempo Aproximado | H73: 5
G74: Tiene que estar en un rango de 10 a 15 minutos
A75: Tiempo Aproximado | B75: 5
A76: Asignacion de Actividades
A77: Resolucion del ejercicio y dudas
A79: Resuelve alguna duda, asigna las actividades que deben realizar, dudas de proyectos, etc

Sheet S.4
B2: Diseño de la Sesión de Laboratorio
B4: Curso | C4: ='Diseño'!C4 -> 787 - Sistemas Organizacionales y Gerenciales 2
B5: Semana | C5: 4
B6: Tiempo | C6: =H10+H21+H51+H75 -> 100
B7: Ponderación | C7: =B56+B67 -> 0
B8: Validación de Tiempo | C8: =IF(H51<=0, "❌ ERROR: La Actividad 1 debe tener un tiempo mayor a 0.", IF(H21>60, "❌ ERROR: El 'Área de Conocimiento' no puede exceder los 60 min.", IF((H10+H21+H51+H75)<100, "❌ ERROR: El tiempo total debe ser de al menos 100 min.", "✅ VALIDACIÓN CORRECTA"))) -> ✅ VALIDACIÓN CORRECTA
A10: 1. Área Actitudinal (Saber Ser) | G10: Tiempo Aproximado | H10: =B13 -> 5
G11: Tiene que estar en un rango de 3 a 5 minutos
A12: Nombre del Valor
A13: Tiempo Aproximado | B13: 5
A14: Descripcion
A17: Como se relaciona con los conocimientos de la sesion y se aplicaria
A21: 2. Área Conocimiento (Saber) | G21: Tiempo Aproximado | H21: =D46+D47+D48+D49 -> 60
G22: No puede exceder los 60 minutos
A23: Competencia a desarrollar | B23: Comprende los fundamentos de la gestión gerencial aplicando teorías administrativas y de liderazgo en el análisis de casos organizacionales
A24: Competencia a desarrollar | B24: Razona procesos de negocio y el uso de algoritmos para la toma de desciones y mapear los procesos utilizando la informacion disponible y herramientas para generar flujos de trabajo y tomar desiciones en base a datos historicos y optimizar procesos
A26: 2.1 Contenido
A27: No. | B27: Unidad | D27: Tema | F27: Sub Tema
A28: 1 | B28: =IFERROR(__xludf.DUMMYFUNCTION("FILTER('Diseño'!D:D,'Diseño'!H:H=$C$5)"),"Unidad 3 IA, Datawarehouse y Datamining") -> Unidad 3 IA, Datawarehouse y Datamining | D28: =IFERROR(__xludf.DUMMYFUNCTION("FILTER('Diseño'!E:E,'Diseño'!H:H=$C$5)"),"Analitica de datos: Datawarehouse") -> Analitica de datos: Datawarehouse | F28: =IFERROR(__xludf.DUMMYFUNCTION("FILTER('Diseño'!F:F,'Diseño'!H:H=$C$5)"),"Conceptos de analiticas y tipos.") -> Conceptos de analiticas y tipos.
A29: 2 | B29: =IFERROR(__xludf.DUMMYFUNCTION("""COMPUTED_VALUE"""),"Unidad 3 IA, Datawarehouse y Datamining") -> Unidad 3 IA, Datawarehouse y Datamining | D29: =IFERROR(__xludf.DUMMYFUNCTION("""COMPUTED_VALUE"""),"Analitica de datos: Datawarehouse") -> Analitica de datos: Datawarehouse | F29: =IFERROR(__xludf.DUMMYFUNCTION("""COMPUTED_VALUE"""),"Conceptos de datawarehouse.") -> Conceptos de datawarehouse.
A30: 3 | B30: =IFERROR(__xludf.DUMMYFUNCTION("""COMPUTED_VALUE"""),"Unidad 3 IA, Datawarehouse y Datamining") -> Unidad 3 IA, Datawarehouse y Datamining | D30: =IFERROR(__xludf.DUMMYFUNCTION("""COMPUTED_VALUE"""),"Analitica de datos: Datawarehouse") -> Analitica de datos: Datawarehouse | F30: =IFERROR(__xludf.DUMMYFUNCTION("""COMPUTED_VALUE"""),"Arquitectura del datawarehouse y su modelo de datos.") -> Arquitectura del datawarehouse y su modelo de datos.
A31: 4 | B31: =IFERROR(__xludf.DUMMYFUNCTION("""COMPUTED_VALUE"""),"Unidad 3 IA, Datawarehouse y Datamining") -> Unidad 3 IA, Datawarehouse y Datamining | D31: =IFERROR(__xludf.DUMMYFUNCTION("""COMPUTED_VALUE"""),"Analitica de datos: Datawarehouse") -> Analitica de datos: Datawarehouse | F31: =IFERROR(__xludf.DUMMYFUNCTION("""COMPUTED_VALUE"""),"Modelos de datos.") -> Modelos de datos.
A32: 5 | B32: =IFERROR(__xludf.DUMMYFUNCTION("""COMPUTED_VALUE"""),"Unidad 3 IA, Datawarehouse y Datamining") -> Unidad 3 IA, Datawarehouse y Datamining | D32: =IFERROR(__xludf.DUMMYFUNCTION("""COMPUTED_VALUE"""),"Analitica de datos: Datawarehouse") -> Analitica de datos: Datawarehouse | F32: =IFERROR(__xludf.DUMMYFUNCTION("""COMPUTED_VALUE"""),"Desafios, recursos e implementación.") -> Desafios, recursos e implementación.
A33: 6 | B33: =IFERROR(__xludf.DUMMYFUNCTION("""COMPUTED_VALUE"""),"Unidad 3 IA, Datawarehouse y Datamining") -> Unidad 3 IA, Datawarehouse y Datamining | D33: =IFERROR(__xludf.DUMMYFUNCTION("""COMPUTED_VALUE"""),"Analitica de datos: Datawarehouse") -> Analitica de datos: Datawarehouse | F33: =IFERROR(__xludf.DUMMYFUNCTION("""COMPUTED_VALUE"""),"Definición del datamining") -> Definición del datamining
A34: 7 | B34: =IFERROR(__xludf.DUMMYFUNCTION("""COMPUTED_VALUE"""),"Unidad 3 IA, Datawarehouse y Datamining") -> Unidad 3 IA, Datawarehouse y Datamining | D34: =IFERROR(__xludf.DUMMYFUNCTION("""COMPUTED_VALUE"""),"Analitica de datos: Datawarehouse") -> Analitica de datos: Datawarehouse | F34: =IFERROR(__xludf.DUMMYFUNCTION("""COMPUTED_VALUE"""),"Técnicas de datamining.") -> Técnicas de datamining.
B35: =IFERROR(__xludf.DUMMYFUNCTION("""COMPUTED_VALUE"""),"Unidad 3 IA, Datawarehouse y Datamining") -> Unidad 3 IA, Datawarehouse y Datamining | D35: =IFERROR(__xludf.DUMMYFUNCTION("""COMPUTED_VALUE"""),"Analitica de datos: Datamining") -> Analitica de datos: Datamining | F35: =IFERROR(__xludf.DUMMYFUNCTION("""COMPUTED_VALUE"""),"Ejemplos de herramientas populares.") -> Ejemplos de herramientas populares.
B36: =IFERROR(__xludf.DUMMYFUNCTION("""COMPUTED_VALUE"""),"Unidad 3 IA, Datawarehouse y Datamining") -> Unidad 3 IA, Datawarehouse y Datamining | D36: =IFERROR(__xludf.DUMMYFUNCTION("""COMPUTED_VALUE"""),"Analitica de datos: Datamining") -> Analitica de datos: Datamining | F36: =IFERROR(__xludf.DUMMYFUNCTION("""COMPUTED_VALUE"""),"Casos de uso en la industria.") -> Casos de uso en la industria.
B37: =IFERROR(__xludf.DUMMYFUNCTION("""COMPUTED_VALUE"""),"Unidad 3 IA, Datawarehouse y Datamining") -> Unidad 3 IA, Datawarehouse y Datamining | D37: =IFERROR(__xludf.DUMMYFUNCTION("""COMPUTED_VALUE"""),"Analitica de datos: Datamining") -> Analitica de datos: Datamining | F37: =IFERROR(__xludf.DUMMYFUNCTION("""COMPUTED_VALUE"""),"Desafíos éticos y de privacidad.") -> Desafíos éticos y de privacidad.
B38: =IFERROR(__xludf.DUMMYFUNCTION("""COMPUTED_VALUE"""),"Unidad 3 IA, Datawarehouse y Datamining") -> Unidad 3 IA, Datawarehouse y Datamining | D38: =IFERROR(__xludf.DUMMYFUNCTION("""COMPUTED_VALUE"""),"Analitica de datos: Datamining") -> Analitica de datos: Datamining | F38: =IFERROR(__xludf.DUMMYFUNCTION("""COMPUTED_VALUE"""),"Definición y propósito.") -> Definición y propósito.
B39: =IFERROR(__xludf.DUMMYFUNCTION("""COMPUTED_VALUE"""),"Unidad 3 IA, Datawarehouse y Datamining") -> Unidad 3 IA, Datawarehouse y Datamining | D39: =IFERROR(__xludf.DUMMYFUNCTION("""COMPUTED_VALUE"""),"Analitica de datos: Datamining") -> Analitica de datos: Datamining | F39: =IFERROR(__xludf.DUMMYFUNCTION("""COMPUTED_VALUE"""),"Perspectivas del balanced scordcard.") -> Perspectivas del balanced scordcard.
B40: =IFERROR(__xludf.DUMMYFUNCTION("""COMPUTED_VALUE"""),"Unidad 3 IA, Datawarehouse y Datamining") -> Unidad 3 IA, Datawarehouse y Datamining | D40: =IFERROR(__xludf.DUMMYFUNCTION("""COMPUTED_VALUE"""),"Analitica de datos: Datamining") -> Analitica de datos: Datamining | F40: =IFERROR(__xludf.DUMMYFUNCTION("""COMPUTED_VALUE"""),"Desarrollo e implementación.") -> Desarrollo e implementación.
B41: =IFERROR(__xludf.DUMMYFUNCTION("""COMPUTED_VALUE"""),"Unidad 3 IA, Datawarehouse y Datamining") -> Unidad 3 IA, Datawarehouse y Datamining | D41: =IFERROR(__xludf.DUMMYFUNCTION("""COMPUTED_VALUE"""),"Analitica de datos: Datamining") -> Analitica de datos: Datamining | F41: =IFERROR(__xludf.DUMMYFUNCTION("""COMPUTED_VALUE"""),"Integración con business intelligence.") -> Integración con business intelligence.
A43: 2.2 Recursos Educativos
A45: Tipo de Recurso a utilizar | B45: Tipo | C45: Rango Aproximando | D45: Tiempo Aproximado
A46: Presentacion | B46: Obligatorio | D46: 20
A47: Video | B47: Obligatorio | C47: 3 a 6 minutos | D47: 10
A48: Lectura | B48: Optativo
A49: Ejercicio Demostrativo | B49: Obligatorio | D49: 30
A51: 3. Área de Habilidades (Saber Hacer) | G51: Tiempo Aproximado | H51: 30
G52: Tiene que estar en un rango de 30 a 50 minutos
A53: Actividad 1 (Obligatoria)
A54: Competencia que predomina en la actividad | B54: Crea propuestas de solución innovadoras utilizando metodologías de diseño estratégico en escenarios empresariales simulados de alta complejidad
A55: Tipo de Actividad | B55: actividades
A56: Ponderación | B56: 0
A57: Tiempo Aproximado | B57: 35
A58: Coloca el tiempo que usar en la actividad, un tiempo sugerido 30 minutos
A59: Descripcion de la Actividad
A60: Analizar un CSV para realizar un ELT con las técnicas y herrramientas vistas en clase
A64: Actividad 2 (Optativa puedes hacerla si lo consideras apropiado)
A65: Competencia que predomina en la actividad
A66: Tipo de Actividad
A67: Ponderación
A68: Tiempo Aproximado
A69: Coloca el tiempo que usar en la actividad, un tiempo sugerido 20 minutos
A70: Descripcion de la Actividad
A75: 3. Cierre | G75: Tiempo Aproximado | H75: 5
G76: Tiene que estar en un rango de 10 a 15 minutos
A77: Tiempo Aproximado | B77: 5
A78: Asignacion de Actividades
A79: Preguntar dificultades con la actividad y sección de preguntas
A81: Resuelve alguna duda, asigna las actividades que deben realizar, dudas de proyectos, etc

Sheet S.5
B2: Diseño de la Sesión de Laboratorio
B4: Curso | C4: ='Diseño'!C4 -> 787 - Sistemas Organizacionales y Gerenciales 2
B5: Semana | C5: 5
B6: Tiempo | C6: =H10+H21+H44+H68 -> 100
B7: Ponderación | C7: =B49+B60 -> 0
B8: Validación de Tiempo | C8: =IF(H44<=0, "❌ ERROR: La Actividad 1 debe tener un tiempo mayor a 0.", IF(H21>60, "❌ ERROR: El 'Área de Conocimiento' no puede exceder los 60 min.", IF((H10+H21+H44)<100, "❌ ERROR: El tiempo total debe ser de al menos 100 min.", "✅ VALIDACIÓN CORRECTA"))) -> ❌ ERROR: El tiempo total debe ser de al menos 100 min.
A10: 1. Área Actitudinal (Saber Ser) | G10: Tiempo Aproximado | H10: =B13 -> 5
G11: Tiene que estar en un rango de 3 a 5 minutos
A12: Nombre del Valor | B12: Trabajo en equipo
A13: Tiempo Aproximado | B13: 5
A14: Descripcion
A15: Colaborar con otros para obtener un análisis más completo y diverso de la información.
A17: Como se relaciona con los conocimientos de la sesion y se aplicaria
A18: En la definición de conceptos y componentes de herramientas BI, el trabajo en equipo permite integrar visiones de distintas áreas para un diseño más efectivo.
A21: 2. Área Conocimiento (Saber) | G21: Tiempo Aproximado | H21: =D39+D40+D41+D42 -> 60
G22: No puede exceder los 60 minutos
A23: Competencia a desarrollar | B23: Recuerda conceptos fundamentales de la administración gerencial realizando la apropiada inteligencia de negos}cios y envontrar brechas para la expansion empresarial y asi lograr los obejtivos que se planificaron desde el principio
A24: Competencia a desarrollar | B24: Analiza oportunidades críticas y de gran valor en un entorno empresarial haciendo uso de matrices y arboles de decisión, así como herramientas para el análisis de datos para definir la mejor planificación y dirección empresarial
A26: 2.1 Contenido
A27: No. | B27: Unidad | D27: Tema | F27: Sub Tema
A28: 1 | B28: =IFERROR(__xludf.DUMMYFUNCTION("FILTER('Diseño'!D:D,'Diseño'!H:H=$C$5)"),"Unidad 3 IA, Datawarehouse y Datamining") -> Unidad 3 IA, Datawarehouse y Datamining | D28: =IFERROR(__xludf.DUMMYFUNCTION("FILTER('Diseño'!E:E,'Diseño'!H:H=$C$5)"),"Analítica de datos: Clasificación de archivos BSC y herramientas de visualización.") -> Analítica de datos: Clasificación de archivos BSC y herramientas de visualización. | F28: =IFERROR(__xludf.DUMMYFUNCTION("FILTER('Diseño'!F:F,'Diseño'!H:H=$C$5)"),"Medición del rendimiento.") -> Medición del rendimiento.
A29: 2 | B29: =IFERROR(__xludf.DUMMYFUNCTION("""COMPUTED_VALUE"""),"Unidad 3 IA, Datawarehouse y Datamining") -> Unidad 3 IA, Datawarehouse y Datamining | D29: =IFERROR(__xludf.DUMMYFUNCTION("""COMPUTED_VALUE"""),"Analítica de datos: Clasificación de archivos BSC y herramientas de visualización.") -> Analítica de datos: Clasificación de archivos BSC y herramientas de visualización. | F29: =IFERROR(__xludf.DUMMYFUNCTION("""COMPUTED_VALUE"""),"Importancia de la visualización de datos.") -> Importancia de la visualización de datos.
A30: 3 | B30: =IFERROR(__xludf.DUMMYFUNCTION("""COMPUTED_VALUE"""),"Unidad 3 IA, Datawarehouse y Datamining") -> Unidad 3 IA, Datawarehouse y Datamining | D30: =IFERROR(__xludf.DUMMYFUNCTION("""COMPUTED_VALUE"""),"Analítica de datos: Clasificación de archivos BSC y herramientas de visualización.") -> Analítica de datos: Clasificación de archivos BSC y herramientas de visualización. | F30: =IFERROR(__xludf.DUMMYFUNCTION("""COMPUTED_VALUE"""),"Conceptos y definición de herramientas BI.") -> Conceptos y definición de herramientas BI.
A31: 4 | B31: =IFERROR(__xludf.DUMMYFUNCTION("""COMPUTED_VALUE"""),"Unidad 3 IA, Datawarehouse y Datamining") -> Unidad 3 IA, Datawarehouse y Datamining | D31: =IFERROR(__xludf.DUMMYFUNCTION("""COMPUTED_VALUE"""),"Analítica de datos: Clasificación de archivos BSC y herramientas de visualización.") -> Analítica de datos: Clasificación de archivos BSC y herramientas de visualización. | F31: =IFERROR(__xludf.DUMMYFUNCTION("""COMPUTED_VALUE"""),"Componentes de las herramientas BI.") -> Componentes de las herramientas BI.
A32: 5 | B32: =IFERROR(__xludf.DUMMYFUNCTION("""COMPUTED_VALUE"""),"Unidad 3 IA, Datawarehouse y Datamining") -> Unidad 3 IA, Datawarehouse y Datamining | D32: =IFERROR(__xludf.DUMMYFUNCTION("""COMPUTED_VALUE"""),"Analítica de datos: Clasificación de archivos BSC y herramientas de visualización.") -> Analítica de datos: Clasificación de archivos BSC y herramientas de visualización. | F32: =IFERROR(__xludf.DUMMYFUNCTION("""COMPUTED_VALUE"""),"Ciclo de vida de las herramientas BI.") -> Ciclo de vida de las herramientas BI.
A33: 6 | B33: =IFERROR(__xludf.DUMMYFUNCTION("""COMPUTED_VALUE"""),"Unidad 3 IA, Datawarehouse y Datamining") -> Unidad 3 IA, Datawarehouse y Datamining | D33: =IFERROR(__xludf.DUMMYFUNCTION("""COMPUTED_VALUE"""),"Analítica de datos: Clasificación de archivos BSC y herramientas de visualización.") -> Analítica de datos: Clasificación de archivos BSC y herramientas de visualización. | F33: =IFERROR(__xludf.DUMMYFUNCTION("""COMPUTED_VALUE"""),"Impacto en la estratégica empresarial.") -> Impacto en la estratégica empresarial.
A34: 7 | B34: =IFERROR(__xludf.DUMMYFUNCTION("""COMPUTED_VALUE"""),"Unidad 3 IA, Datawarehouse y Datamining") -> Unidad 3 IA, Datawarehouse y Datamining | D34: =IFERROR(__xludf.DUMMYFUNCTION("""COMPUTED_VALUE"""),"Analítica de datos: Clasificación de archivos BSC y herramientas de visualización.") -> Analítica de datos: Clasificación de archivos BSC y herramientas de visualización. | F34: =IFERROR(__xludf.DUMMYFUNCTION("""COMPUTED_VALUE"""),"Tipos de visualizaciones.") -> Tipos de visualizaciones.
A36: 2.2 Recursos Educativos
A38: Tipo de Recurso a utilizar | B38: Tipo | C38: Rango Aproximando | D38: Tiempo Aproximado
A39: Presentacion | B39: Obligatorio | D39: 20
A40: Video | B40: Obligatorio | C40: 3 a 6 minutos | D40: 10
A41: Lectura | B41: Optativo | D41: 20
A42: Ejercicio Demostrativo | B42: Obligatorio | D42: 10
A44: 3. Área de Habilidades (Saber Hacer) | G44: Tiempo Aproximado | H44: 30
G45: Tiene que estar en un rango de 30 a 50 minutos
A46: Actividad 1 (Obligatoria)
A47: Competencia que predomina en la actividad | B47: Crea ..
A48: Tipo de Actividad | B48: actividades
A49: Ponderación | B49: 0
A50: Tiempo Aproximado | B50: 35
A51: Coloca el tiempo que usar en la actividad, un tiempo sugerido 30 minutos
A52: Descripcion de la Actividad
A53: Realizar 2 dashboard con información relevante de datos extraidos en la web utilizando power BI
A57: Actividad 2 (Optativa puedes hacerla si lo consideras apropiado)
A58: Competencia que predomina en la actividad
A59: Tipo de Actividad
A60: Ponderación
A61: Tiempo Aproximado
A62: Coloca el tiempo que usar en la actividad, un tiempo sugerido 20 minutos
A63: Descripcion de la Actividad
A68: 3. Cierre | G68: Tiempo Aproximado | H68: 5
G69: Tiene que estar en un rango de 10 a 15 minutos
A70: Tiempo Aproximado | B70: 5
A71: Asignacion de Actividades
A72: Sección de preguntas
A74: Resuelve alguna duda, asigna las actividades que deben realizar, dudas de proyectos, etc

Sheet S.6
B2: Diseño de la Sesión de Laboratorio
B4: Curso | C4: ='Diseño'!C4 -> 787 - Sistemas Organizacionales y Gerenciales 2
B5: Semana | C5: 6
B6: Tiempo | C6: =H10+H21+H44+H68 -> 100
B7: Ponderación | C7: =B49+B60 -> 0
B8: Validación de Tiempo | C8: =IF(H44<=0, "❌ ERROR: La Actividad 1 debe tener un tiempo mayor a 0.", IF(H21>60, "❌ ERROR: El 'Área de Conocimiento' no puede exceder los 60 min.", IF((H10+H21+H44)<100, "❌ ERROR: El tiempo total debe ser de al menos 100 min.", "✅ VALIDACIÓN CORRECTA"))) -> ❌ ERROR: El tiempo total debe ser de al menos 100 min.
A10: 1. Área Actitudinal (Saber Ser) | G10: Tiempo Aproximado | H10: =B13 -> 5
G11: Tiene que estar en un rango de 3 a 5 minutos
A12: Nombre del Valor | B12: Colaboración
A13: Tiempo Aproximado | B13: 5
A14: Descripcion
A15: Trabajar en conjunto con compañeros y equipos de diferentes áreas, compartiendo información y aportes que enriquezcan el uso de herramientas BI y el diseño de workflows.
A17: Como se relaciona con los conocimientos de la sesion y se aplicaria
A18: La colaboración permite integrar diversas perspectivas al aplicar buenas prácticas de Business Intelligence, definir roles dentro de un workflow y garantizar que los procesos empresariales funcionen de manera eficiente y coordinada.
A21: 2. Área Conocimiento (Saber) | G21: Tiempo Aproximado | H21: =D39+D40+D41+D42 -> 60
G22: No puede exceder los 60 minutos
A23: Competencia a desarrollar | B23: Implementa utilizando Workflows para entandarizar utilizando Workflows para entandarizar los procesos de transformacion digital aplicando normas internacionales
A24: Competencia a desarrollar | B24: Razona procesos de negocio y el uso de algoritmos para la toma de desciones y mapear los procesos utilizando la informacion disponible y herramientas para generar flujos de trabajo y tomar desiciones en base a datos historicos y optimizar procesos
A26: 2.1 Contenido
A27: No. | B27: Unidad | D27: Tema | F27: Sub Tema
A28: 1 | B28: =IFERROR(__xludf.DUMMYFUNCTION("FILTER('Diseño'!D:D,'Diseño'!H:H=$C$5)"),"Unidad 4 Business Intelligence y Workflow") -> Unidad 4 Business Intelligence y Workflow | D28: =IFERROR(__xludf.DUMMYFUNCTION("FILTER('Diseño'!E:E,'Diseño'!H:H=$C$5)"),"Business Intelligence y modelos de workflow") -> Business Intelligence y modelos de workflow | F28: =IFERROR(__xludf.DUMMYFUNCTION("FILTER('Diseño'!F:F,'Diseño'!H:H=$C$5)"),"Beneficios de herramientas BI e integración con sistemas datawarehouse y datamining.") -> Beneficios de herramientas BI e integración con sistemas datawarehouse y datamining.
A29: 2 | B29: =IFERROR(__xludf.DUMMYFUNCTION("""COMPUTED_VALUE"""),"Unidad 4 Business Intelligence y Workflow") -> Unidad 4 Business Intelligence y Workflow | D29: =IFERROR(__xludf.DUMMYFUNCTION("""COMPUTED_VALUE"""),"Business Intelligence y modelos de workflow") -> Business Intelligence y modelos de workflow | F29: =IFERROR(__xludf.DUMMYFUNCTION("""COMPUTED_VALUE"""),"Buenas prácticas.") -> Buenas prácticas.
A30: 3 | B30: =IFERROR(__xludf.DUMMYFUNCTION("""COMPUTED_VALUE"""),"Unidad 4 Business Intelligence y Workflow") -> Unidad 4 Business Intelligence y Workflow | D30: =IFERROR(__xludf.DUMMYFUNCTION("""COMPUTED_VALUE"""),"Business Intelligence y modelos de workflow") -> Business Intelligence y modelos de workflow | F30: =IFERROR(__xludf.DUMMYFUNCTION("""COMPUTED_VALUE"""),"Ejemplos de herramientas BI y beneficios.") -> Ejemplos de herramientas BI y beneficios.
A31: 4 | B31: =IFERROR(__xludf.DUMMYFUNCTION("""COMPUTED_VALUE"""),"Unidad 4 Business Intelligence y Workflow") -> Unidad 4 Business Intelligence y Workflow | D31: =IFERROR(__xludf.DUMMYFUNCTION("""COMPUTED_VALUE"""),"Business Intelligence y modelos de workflow") -> Business Intelligence y modelos de workflow | F31: =IFERROR(__xludf.DUMMYFUNCTION("""COMPUTED_VALUE"""),"Definición de workflow.") -> Definición de workflow.
A32: 5 | B32: =IFERROR(__xludf.DUMMYFUNCTION("""COMPUTED_VALUE"""),"Unidad 4 Business Intelligence y Workflow") -> Unidad 4 Business Intelligence y Workflow | D32: =IFERROR(__xludf.DUMMYFUNCTION("""COMPUTED_VALUE"""),"Business Intelligence y modelos de workflow") -> Business Intelligence y modelos de workflow | F32: =IFERROR(__xludf.DUMMYFUNCTION("""COMPUTED_VALUE"""),"Componentes del workflow, tareas, roles, recursos.") -> Componentes del workflow, tareas, roles, recursos.
A33: 6 | B33: =IFERROR(__xludf.DUMMYFUNCTION("""COMPUTED_VALUE"""),"Unidad 4 Business Intelligence y Workflow") -> Unidad 4 Business Intelligence y Workflow | D33: =IFERROR(__xludf.DUMMYFUNCTION("""COMPUTED_VALUE"""),"Business Intelligence y modelos de workflow") -> Business Intelligence y modelos de workflow | F33: =IFERROR(__xludf.DUMMYFUNCTION("""COMPUTED_VALUE"""),"Tipos de workflow (estructurados, no estructurados).") -> Tipos de workflow (estructurados, no estructurados).
A34: 7 | B34: =IFERROR(__xludf.DUMMYFUNCTION("""COMPUTED_VALUE"""),"Unidad 4 Business Intelligence y Workflow") -> Unidad 4 Business Intelligence y Workflow | D34: =IFERROR(__xludf.DUMMYFUNCTION("""COMPUTED_VALUE"""),"Business Intelligence y modelos de workflow") -> Business Intelligence y modelos de workflow | F34: =IFERROR(__xludf.DUMMYFUNCTION("""COMPUTED_VALUE"""),"Tipos de workflow (horizontal, vertical)") -> Tipos de workflow (horizontal, vertical)
A36: 2.2 Recursos Educativos
A38: Tipo de Recurso a utilizar | B38: Tipo | C38: Rango Aproximando | D38: Tiempo Aproximado
A39: Presentacion | B39: Obligatorio | D39: 25
A40: Video | B40: Obligatorio | C40: 3 a 6 minutos | D40: 5
A41: Lectura | B41: Optativo
A42: Ejercicio Demostrativo | B42: Obligatorio | D42: 30
A44: 3. Área de Habilidades (Saber Hacer) | G44: Tiempo Aproximado | H44: 30
G45: Tiene que estar en un rango de 30 a 50 minutos
A46: Actividad 1 (Obligatoria)
A47: Competencia que predomina en la actividad | B47: Crea ..
A48: Tipo de Actividad | B48: actividades
A49: Ponderación | B49: 0
A50: Tiempo Aproximado | B50: 35
A51: Coloca el tiempo que usar en la actividad, un tiempo sugerido 30 minutos
A52: Descripcion de la Actividad
A53: Ejemplificar un workflow secuencial y uno por eventos
A57: Actividad 2 (Optativa puedes hacerla si lo consideras apropiado)
A58: Competencia que predomina en la actividad
A59: Tipo de Actividad
A60: Ponderación
A61: Tiempo Aproximado
A62: Coloca el tiempo que usar en la actividad, un tiempo sugerido 20 minutos
A63: Descripcion de la Actividad
A68: 3. Cierre | G68: Tiempo Aproximado | H68: 5
G69: Tiene que estar en un rango de 10 a 15 minutos
A70: Tiempo Aproximado | B70: 5
A71: Asignacion de Actividades
A72: Resolver/explicar el ejercicio y sección de preguntas
A74: Resuelve alguna duda, asigna las actividades que deben realizar, dudas de proyectos, etc

Sheet S.7
B2: Diseño de la Sesión de Laboratorio
B4: Curso | C4: ='Diseño'!C4 -> 787 - Sistemas Organizacionales y Gerenciales 2
B5: Semana | C5: 7
B6: Tiempo | C6: =H10+H21+H44+H68 -> 100
B7: Ponderación | C7: =B49+B60 -> 0
B8: Validación de Tiempo | C8: =IF(H44<=0, "❌ ERROR: La Actividad 1 debe tener un tiempo mayor a 0.", IF(H21>60, "❌ ERROR: El 'Área de Conocimiento' no puede exceder los 60 min.", IF((H10+H21+H44)=100, "❌ ERROR: El tiempo total debe ser de al menos 100 min.", "✅ VALIDACIÓN CORRECTA"))) -> ✅ VALIDACIÓN CORRECTA
A10: 1. Área Actitudinal (Saber Ser) | G10: Tiempo Aproximado | H10: 10
G11: Tiene que estar en un rango de 3 a 5 minutos
A12: Nombre del Valor | B12: Transparencia
A13: Tiempo Aproximado
A14: Descripcion
A15: La transparencia es un valor clave en la gestión del BPO y la subcontratación tecnológica, esencial para fortalecer la confianza entre las partes y garantizar la ética en los acuerdos.
A17: Como se relaciona con los conocimientos de la sesion y se aplicaria
A18: Desde la gerencia, facilita la evaluación clara de resultados y la reducción de riesgos. Para los estudiantes, implica cultivar la comunicación honesta, la responsabilidad en el manejo de información y la supervisión rigurosa de procesos, preparándolos para liderar con integridad en el ámbito empresarial.
A21: 2. Área Conocimiento (Saber) | G21: Tiempo Aproximado | H21: 50
G22: No puede exceder los 60 minutos
A23: Competencia a desarrollar | B23: Analiza oportunidades críticas y de gran valor en un entorno empresarial haciendo uso de matrices y arboles de decisión, así como herramientas para el análisis de datos para definir la mejor planificación y dirección empresarial
A24: Competencia a desarrollar | B24: Razona procesos de negocio y el uso de algoritmos para la toma de desciones y mapear los procesos utilizando la informacion disponible y herramientas para generar flujos de trabajo y tomar desiciones en base a datos historicos y optimizar procesos
A26: 2.1 Contenido
A27: No. | B27: Unidad | D27: Tema | F27: Sub Tema
A28: 1 | B28: =IFERROR(__xludf.DUMMYFUNCTION("FILTER('Diseño'!D:D,'Diseño'!H:H=$C$5)"),"Unidad 5 Gestión documental y Modelos de Workflow BPO") -> Unidad 5 Gestión documental y Modelos de Workflow BPO | D28: =IFERROR(__xludf.DUMMYFUNCTION("FILTER('Diseño'!E:E,'Diseño'!H:H=$C$5)"),"Modelos de Workflow: Definiciones clave y principios de mejora eficiencia.") -> Modelos de Workflow: Definiciones clave y principios de mejora eficiencia. | F28: =IFERROR(__xludf.DUMMYFUNCTION("FILTER('Diseño'!F:F,'Diseño'!H:H=$C$5)"),"Beneficios del uso de workflow: Eficiencia, comunicación, reducción de errores.") -> Beneficios del uso de workflow: Eficiencia, comunicación, reducción de errores.
A29: 2 | B29: =IFERROR(__xludf.DUMMYFUNCTION("""COMPUTED_VALUE"""),"Unidad 5 Gestión documental y Modelos de Workflow BPO") -> Unidad 5 Gestión documental y Modelos de Workflow BPO | D29: =IFERROR(__xludf.DUMMYFUNCTION("""COMPUTED_VALUE"""),"Modelos de Workflow: Definiciones clave y principios de mejora eficiencia.") -> Modelos de Workflow: Definiciones clave y principios de mejora eficiencia. | F29: =IFERROR(__xludf.DUMMYFUNCTION("""COMPUTED_VALUE"""),"Definiciones clave.") -> Definiciones clave.
A30: 3 | B30: =IFERROR(__xludf.DUMMYFUNCTION("""COMPUTED_VALUE"""),"Unidad 5 Gestión documental y Modelos de Workflow BPO") -> Unidad 5 Gestión documental y Modelos de Workflow BPO | D30: =IFERROR(__xludf.DUMMYFUNCTION("""COMPUTED_VALUE"""),"Modelos de Workflow: Definiciones clave y principios de mejora eficiencia.") -> Modelos de Workflow: Definiciones clave y principios de mejora eficiencia. | F30: =IFERROR(__xludf.DUMMYFUNCTION("""COMPUTED_VALUE"""),"Ciclo de vida del documento.") -> Ciclo de vida del documento.
A31: 4 | B31: =IFERROR(__xludf.DUMMYFUNCTION("""COMPUTED_VALUE"""),"Unidad 5 Gestión documental y Modelos de Workflow BPO") -> Unidad 5 Gestión documental y Modelos de Workflow BPO | D31: =IFERROR(__xludf.DUMMYFUNCTION("""COMPUTED_VALUE"""),"Modelos de Workflow: Definiciones clave y principios de mejora eficiencia.") -> Modelos de Workflow: Definiciones clave y principios de mejora eficiencia. | F31: =IFERROR(__xludf.DUMMYFUNCTION("""COMPUTED_VALUE"""),"Normativas y estándares, internos y externos.") -> Normativas y estándares, internos y externos.
A32: 5 | B32: =IFERROR(__xludf.DUMMYFUNCTION("""COMPUTED_VALUE"""),"Unidad 5 Gestión documental y Modelos de Workflow BPO") -> Unidad 5 Gestión documental y Modelos de Workflow BPO | D32: =IFERROR(__xludf.DUMMYFUNCTION("""COMPUTED_VALUE"""),"Modelos de Workflow: Definiciones clave y principios de mejora eficiencia.") -> Modelos de Workflow: Definiciones clave y principios de mejora eficiencia. | F32: =IFERROR(__xludf.DUMMYFUNCTION("""COMPUTED_VALUE"""),"Normativas y estándars internacionales.") -> Normativas y estándars internacionales.
A33: 6 | B33: =IFERROR(__xludf.DUMMYFUNCTION("""COMPUTED_VALUE"""),"Unidad 5 Gestión documental y Modelos de Workflow BPO") -> Unidad 5 Gestión documental y Modelos de Workflow BPO | D33: =IFERROR(__xludf.DUMMYFUNCTION("""COMPUTED_VALUE"""),"Modelos de Workflow: Definiciones clave y principios de mejora eficiencia.") -> Modelos de Workflow: Definiciones clave y principios de mejora eficiencia. | F33: =IFERROR(__xludf.DUMMYFUNCTION("""COMPUTED_VALUE"""),"Calidad de la documentación.") -> Calidad de la documentación.
A34: 7 | B34: =IFERROR(__xludf.DUMMYFUNCTION("""COMPUTED_VALUE"""),"Unidad 5 Gestión documental y Modelos de Workflow BPO") -> Unidad 5 Gestión documental y Modelos de Workflow BPO | D34: =IFERROR(__xludf.DUMMYFUNCTION("""COMPUTED_VALUE"""),"Modelos de Workflow: Definiciones clave y principios de mejora eficiencia.") -> Modelos de Workflow: Definiciones clave y principios de mejora eficiencia. | F34: =IFERROR(__xludf.DUMMYFUNCTION("""COMPUTED_VALUE"""),"Ejemplos de workflow.") -> Ejemplos de workflow.
B35: =IFERROR(__xludf.DUMMYFUNCTION("""COMPUTED_VALUE"""),"Unidad 5 Gestión documental y Modelos de Workflow BPO") -> Unidad 5 Gestión documental y Modelos de Workflow BPO | D35: =IFERROR(__xludf.DUMMYFUNCTION("""COMPUTED_VALUE"""),"Modelos Workflow: Integración, gestión documental y transformación digital.") -> Modelos Workflow: Integración, gestión documental y transformación digital. | F35: =IFERROR(__xludf.DUMMYFUNCTION("""COMPUTED_VALUE"""),"Desarrollo y correcto flujo de los documentos.") -> Desarrollo y correcto flujo de los documentos.
A36: 2.2 Recursos Educativos
A38: Tipo de Recurso a utilizar | B38: Tipo | C38: Rango Aproximando | D38: Tiempo Aproximado
A39: Presentacion | B39: Obligatorio | C39: 2 min
A40: Video | B40: Obligatorio | C40: 5 a 6 min
A41: Lectura | B41: Optativo
A42: Ejercicio Demostrativo | B42: Obligatorio | C42: 10min
A44: 3. Área de Habilidades (Saber Hacer) | G44: Tiempo Aproximado | H44: 20
G45: Tiene que estar en un rango de 30 a 50 minutos
A46: Actividad 1 (Obligatoria)
A47: Competencia que predomina en la actividad | B47: Crea ..
A48: Tipo de Actividad | B48: actividades
A49: Ponderación | B49: 0
A50: Tiempo Aproximado | B50: 0
A51: Coloca el tiempo que usar en la actividad, un tiempo sugerido 30 minutos
A52: Descripcion de la Actividad
A53: demostracion de las herramientas y normativos aplicados en escenarios reales
A57: Actividad 2 (Optativa puedes hacerla si lo consideras apropiado)
A58: Competencia que predomina en la actividad
A59: Tipo de Actividad
A60: Ponderación
A61: Tiempo Aproximado
A62: Coloca el tiempo que usar en la actividad, un tiempo sugerido 20 minutos
A63: Descripcion de la Actividad
A68: 3. Cierre | G68: Tiempo Aproximado | H68: 20
G69: Tiene que estar en un rango de 10 a 15 minutos
A70: Tiempo Aproximado
A71: Asignacion de Actividades
A72: conclusiones, recomendaciones y recordatorios de actividades
A74: Resuelve alguna duda, asigna las actividades que deben realizar, dudas de proyectos, etc

Sheet S.8
B2: Diseño de la Sesión de Laboratorio
B4: Curso | C4: ='Diseño'!C4 -> 787 - Sistemas Organizacionales y Gerenciales 2
B5: Semana | C5: 8
B6: Tiempo | C6: =H10+H21+H44+H68 -> 100
B7: Ponderación | C7: =B49+B60 -> 0
B8: Validación de Tiempo | C8: =IF(H44<=0, "❌ ERROR: La Actividad 1 debe tener un tiempo mayor a 0.", IF(H21>60, "❌ ERROR: El 'Área de Conocimiento' no puede exceder los 60 min.", IF((H10+H21+H44)=100, "❌ ERROR: El tiempo total debe ser de al menos 100 min.", "✅ VALIDACIÓN CORRECTA"))) -> ✅ VALIDACIÓN CORRECTA
A10: 1. Área Actitudinal (Saber Ser) | G10: Tiempo Aproximado | H10: 10
G11: Tiene que estar en un rango de 3 a 5 minutos
A12: Nombre del Valor | B12: Transparencia
A13: Tiempo Aproximado
A14: Descripcion
A15: La transparencia es un valor clave en la gestión del BPO y la subcontratación tecnológica, esencial para fortalecer la confianza entre las partes y garantizar la ética en los acuerdos.
A17: Como se relaciona con los conocimientos de la sesion y se aplicaria
A18: Desde la gerencia, facilita la evaluación clara de resultados y la reducción de riesgos. Para los estudiantes, implica cultivar la comunicación honesta, la responsabilidad en el manejo de información y la supervisión rigurosa de procesos, preparándolos para liderar con integridad en el ámbito empresarial.
A21: 2. Área Conocimiento (Saber) | G21: Tiempo Aproximado | H21: 45
G22: No puede exceder los 60 minutos
A23: Competencia a desarrollar | B23: Razona procesos de negocio y el uso de algoritmos para la toma de desciones y mapear los procesos utilizando la informacion disponible y herramientas para generar flujos de trabajo y tomar desiciones en base a datos historicos y optimizar procesos
A24: Competencia a desarrollar | B24: Implementa utilizando Workflows para entandarizar utilizando Workflows para entandarizar los procesos de transformacion digital aplicando normas internacionales
A26: 2.1 Contenido
A27: No. | B27: Unidad | D27: Tema | F27: Sub Tema
A28: 1 | B28: =IFERROR(__xludf.DUMMYFUNCTION("FILTER('Diseño'!D:D,'Diseño'!H:H=$C$5)"),"Unidad 5 Gestión documental y Modelos de Workflow BPO") -> Unidad 5 Gestión documental y Modelos de Workflow BPO | D28: =IFERROR(__xludf.DUMMYFUNCTION("FILTER('Diseño'!E:E,'Diseño'!H:H=$C$5)"),"Modelos Workflow: Integración, gestión documental y transformación digital.") -> Modelos Workflow: Integración, gestión documental y transformación digital. | F28: =IFERROR(__xludf.DUMMYFUNCTION("FILTER('Diseño'!F:F,'Diseño'!H:H=$C$5)"),"Desafios de integración.") -> Desafios de integración.
A29: 2 | B29: =IFERROR(__xludf.DUMMYFUNCTION("""COMPUTED_VALUE"""),"Unidad 5 Gestión documental y Modelos de Workflow BPO") -> Unidad 5 Gestión documental y Modelos de Workflow BPO | D29: =IFERROR(__xludf.DUMMYFUNCTION("""COMPUTED_VALUE"""),"Modelos Workflow: Integración, gestión documental y transformación digital.") -> Modelos Workflow: Integración, gestión documental y transformación digital. | F29: =IFERROR(__xludf.DUMMYFUNCTION("""COMPUTED_VALUE"""),"Impacto en la transformación digital.") -> Impacto en la transformación digital.
A30: 3 | B30: =IFERROR(__xludf.DUMMYFUNCTION("""COMPUTED_VALUE"""),"Unidad 5 Gestión documental y Modelos de Workflow BPO") -> Unidad 5 Gestión documental y Modelos de Workflow BPO | D30: =IFERROR(__xludf.DUMMYFUNCTION("""COMPUTED_VALUE"""),"Modelos Workflow: Integración, gestión documental y transformación digital.") -> Modelos Workflow: Integración, gestión documental y transformación digital. | F30: =IFERROR(__xludf.DUMMYFUNCTION("""COMPUTED_VALUE"""),"Estratégias para la adaptación a la transformación digital.") -> Estratégias para la adaptación a la transformación digital.
A31: 4 | B31: =IFERROR(__xludf.DUMMYFUNCTION("""COMPUTED_VALUE"""),"Unidad 5 Gestión documental y Modelos de Workflow BPO") -> Unidad 5 Gestión documental y Modelos de Workflow BPO | D31: =IFERROR(__xludf.DUMMYFUNCTION("""COMPUTED_VALUE"""),"Modelos Workflow: Integración, gestión documental y transformación digital.") -> Modelos Workflow: Integración, gestión documental y transformación digital. | F31: =IFERROR(__xludf.DUMMYFUNCTION("""COMPUTED_VALUE"""),"Evalución de resultados.") -> Evalución de resultados.
A32: 5 | B32: =IFERROR(__xludf.DUMMYFUNCTION("""COMPUTED_VALUE"""),"Unidad 5 Gestión documental y Modelos de Workflow BPO") -> Unidad 5 Gestión documental y Modelos de Workflow BPO | D32: =IFERROR(__xludf.DUMMYFUNCTION("""COMPUTED_VALUE"""),"Modelos Workflow: Integración, gestión documental y transformación digital.") -> Modelos Workflow: Integración, gestión documental y transformación digital. | F32: =IFERROR(__xludf.DUMMYFUNCTION("""COMPUTED_VALUE"""),"Tendencias actuales de gestión documental.") -> Tendencias actuales de gestión documental.
A33: 6 | B33: =IFERROR(__xludf.DUMMYFUNCTION("""COMPUTED_VALUE"""),"Unidad 5 Gestión documental y Modelos de Workflow BPO") -> Unidad 5 Gestión documental y Modelos de Workflow BPO | D33: =IFERROR(__xludf.DUMMYFUNCTION("""COMPUTED_VALUE"""),"Conceptos y beneficios de Business Process Outsourcing (BPO)") -> Conceptos y beneficios de Business Process Outsourcing (BPO) | F33: =IFERROR(__xludf.DUMMYFUNCTION("""COMPUTED_VALUE"""),"Conceptos, beneficios, alcance del BPO.") -> Conceptos, beneficios, alcance del BPO.
A34: 7 | B34: =IFERROR(__xludf.DUMMYFUNCTION("""COMPUTED_VALUE"""),"Unidad 5 Gestión documental y Modelos de Workflow BPO") -> Unidad 5 Gestión documental y Modelos de Workflow BPO | D34: =IFERROR(__xludf.DUMMYFUNCTION("""COMPUTED_VALUE"""),"Conceptos y beneficios de Business Process Outsourcing (BPO)") -> Conceptos y beneficios de Business Process Outsourcing (BPO) | F34: =IFERROR(__xludf.DUMMYFUNCTION("""COMPUTED_VALUE"""),"Impacto en la subcontratación de servicios tecnológicos.") -> Impacto en la subcontratación de servicios tecnológicos.
B35: =IFERROR(__xludf.DUMMYFUNCTION("""COMPUTED_VALUE"""),"Unidad 5 Gestión documental y Modelos de Workflow BPO") -> Unidad 5 Gestión documental y Modelos de Workflow BPO | D35: =IFERROR(__xludf.DUMMYFUNCTION("""COMPUTED_VALUE"""),"Conceptos y beneficios de Business Process Outsourcing (BPO)") -> Conceptos y beneficios de Business Process Outsourcing (BPO) | F35: =IFERROR(__xludf.DUMMYFUNCTION("""COMPUTED_VALUE"""),"Impacto en la subcontratación: oportunidades, desafíos.") -> Impacto en la subcontratación: oportunidades, desafíos.
A36: 2.2 Recursos Educativos | B36: =IFERROR(__xludf.DUMMYFUNCTION("""COMPUTED_VALUE"""),"Unidad 5 Gestión documental y Modelos de Workflow BPO") -> Unidad 5 Gestión documental y Modelos de Workflow BPO | D36: =IFERROR(__xludf.DUMMYFUNCTION("""COMPUTED_VALUE"""),"Conceptos y beneficios de Business Process Outsourcing (BPO)") -> Conceptos y beneficios de Business Process Outsourcing (BPO) | F36: =IFERROR(__xludf.DUMMYFUNCTION("""COMPUTED_VALUE"""),"Análisis de costos.") -> Análisis de costos.
A38: Tipo de Recurso a utilizar | B38: Tipo | C38: Rango Aproximando | D38: Tiempo Aproximado
A39: Presentacion | B39: Obligatorio
A40: Video | B40: Obligatorio | C40: 3 a 6 minutos
A41: Lectura | B41: Optativo
A42: Ejercicio Demostrativo | B42: Obligatorio
A44: 3. Área de Habilidades (Saber Hacer) | G44: Tiempo Aproximado | H44: 30
G45: Tiene que estar en un rango de 30 a 50 minutos
A46: Actividad 1 (Obligatoria)
A47: Competencia que predomina en la actividad | B47: Crea ..
A48: Tipo de Actividad | B48: actividades
A49: Ponderación | B49: 0
A50: Tiempo Aproximado | B50: 10
A51: Coloca el tiempo que usar en la actividad, un tiempo sugerido 30 minutos
A52: Descripcion de la Actividad
A53: demostracion de las herramientas y normativos aplicados en escenarios reales
A57: Actividad 2 (Optativa puedes hacerla si lo consideras apropiado)
A58: Competencia que predomina en la actividad
A59: Tipo de Actividad
A60: Ponderación
A61: Tiempo Aproximado
A62: Coloca el tiempo que usar en la actividad, un tiempo sugerido 20 minutos
A63: Descripcion de la Actividad
A68: 3. Cierre | G68: Tiempo Aproximado | H68: 15
G69: Tiene que estar en un rango de 10 a 15 minutos
A70: Tiempo Aproximado
A71: Asignacion de Actividades
A72: conclusiones, recomendaciones y recordatorios de actividades
A74: Resuelve alguna duda, asigna las actividades que deben realizar, dudas de proyectos, etc

Sheet S.9
B2: Diseño de la Sesión de Laboratorio
B4: Curso | C4: ='Diseño'!C4 -> 787 - Sistemas Organizacionales y Gerenciales 2
B5: Semana | C5: 9
B6: Tiempo | C6: =H10+H21+H44+H68 -> 110
B7: Ponderación | C7: =B49+B60 -> 0
B8: Validación de Tiempo | C8: =IF(H44<=0, "❌ ERROR: La Actividad 1 debe tener un tiempo mayor a 0.", IF(H21>60, "❌ ERROR: El 'Área de Conocimiento' no puede exceder los 60 min.", IF((H10+H21+H44)<100, "❌ ERROR: El tiempo total debe ser de al menos 100 min.", "✅ VALIDACIÓN CORRECTA"))) -> ❌ ERROR: El tiempo total debe ser de al menos 100 min.
A10: 1. Área Actitudinal (Saber Ser) | G10: Tiempo Aproximado | H10: 10
G11: Tiene que estar en un rango de 3 a 5 minutos
A12: Nombre del Valor | B12: Responsabilidad
A13: Tiempo Aproximado
A14: Descripcion
A15: Implica asegurar que las implementaciones sean éticas, seguras y alineadas con los objetivos organizacionales.
A17: Como se relaciona con los conocimientos de la sesion y se aplicaria
A18: Para el estudiante, representa el compromiso de aplicar correctamente las tecnologías RPA, protegiendo la integridad de los datos y considerando el impacto en personas y procesos. Este valor fortalece su formación profesional y ética durante el semestre.
A21: 2. Área Conocimiento (Saber) | G21: Tiempo Aproximado | H21: 60
G22: No puede exceder los 60 minutos
A23: Competencia a desarrollar
A24: Competencia a desarrollar
A26: 2.1 Contenido
A27: No. | B27: Unidad | D27: Tema | F27: Sub Tema
A28: 1 | B28: =IFERROR(__xludf.DUMMYFUNCTION("FILTER('Diseño'!D:D,'Diseño'!H:H=$C$5)"),"Unidad 5 Gestión documental y Modelos de Workflow BPO") -> Unidad 5 Gestión documental y Modelos de Workflow BPO | D28: =IFERROR(__xludf.DUMMYFUNCTION("FILTER('Diseño'!E:E,'Diseño'!H:H=$C$5)"),"Conceptos y beneficios de Business Process Outsourcing (BPO)") -> Conceptos y beneficios de Business Process Outsourcing (BPO) | F28: =IFERROR(__xludf.DUMMYFUNCTION("FILTER('Diseño'!F:F,'Diseño'!H:H=$C$5)"),"Selección del proveedor y estudios de proveedores.") -> Selección del proveedor y estudios de proveedores.
A29: 2 | B29: =IFERROR(__xludf.DUMMYFUNCTION("""COMPUTED_VALUE"""),"Unidad 5 Gestión documental y Modelos de Workflow BPO") -> Unidad 5 Gestión documental y Modelos de Workflow BPO | D29: =IFERROR(__xludf.DUMMYFUNCTION("""COMPUTED_VALUE"""),"Conceptos y beneficios de Business Process Outsourcing (BPO)") -> Conceptos y beneficios de Business Process Outsourcing (BPO) | F29: =IFERROR(__xludf.DUMMYFUNCTION("""COMPUTED_VALUE"""),"Control de calidad y gestión de relación.") -> Control de calidad y gestión de relación.
A30: 3 | B30: =IFERROR(__xludf.DUMMYFUNCTION("""COMPUTED_VALUE"""),"Unidad 5 Gestión documental y Modelos de Workflow BPO") -> Unidad 5 Gestión documental y Modelos de Workflow BPO | D30: =IFERROR(__xludf.DUMMYFUNCTION("""COMPUTED_VALUE"""),"Conceptos y beneficios de Business Process Outsourcing (BPO)") -> Conceptos y beneficios de Business Process Outsourcing (BPO) | F30: =IFERROR(__xludf.DUMMYFUNCTION("""COMPUTED_VALUE"""),"Seguridad, cumplimientos y acuerdos.") -> Seguridad, cumplimientos y acuerdos.
A31: 4 | B31: =IFERROR(__xludf.DUMMYFUNCTION("""COMPUTED_VALUE"""),"Unidad 6 Automatización de procesos empresariales.") -> Unidad 6 Automatización de procesos empresariales. | D31: =IFERROR(__xludf.DUMMYFUNCTION("""COMPUTED_VALUE"""),"Introducción a la automatización.") -> Introducción a la automatización. | F31: =IFERROR(__xludf.DUMMYFUNCTION("""COMPUTED_VALUE"""),"Impacto interno, flexibilidad y escalabilidad.") -> Impacto interno, flexibilidad y escalabilidad.
A32: 5 | B32: =IFERROR(__xludf.DUMMYFUNCTION("""COMPUTED_VALUE"""),"Unidad 6 Automatización de procesos empresariales.") -> Unidad 6 Automatización de procesos empresariales. | D32: =IFERROR(__xludf.DUMMYFUNCTION("""COMPUTED_VALUE"""),"Introducción a la automatización.") -> Introducción a la automatización. | F32: =IFERROR(__xludf.DUMMYFUNCTION("""COMPUTED_VALUE"""),"Medición de resultados y tendencias futuras.") -> Medición de resultados y tendencias futuras.
A33: 6 | B33: =IFERROR(__xludf.DUMMYFUNCTION("""COMPUTED_VALUE"""),"Unidad 6 Automatización de procesos empresariales.") -> Unidad 6 Automatización de procesos empresariales. | D33: =IFERROR(__xludf.DUMMYFUNCTION("""COMPUTED_VALUE"""),"Introducción a la automatización.") -> Introducción a la automatización. | F33: =IFERROR(__xludf.DUMMYFUNCTION("""COMPUTED_VALUE"""),"Introducción a la automatización.") -> Introducción a la automatización.
A34: 7 | B34: =IFERROR(__xludf.DUMMYFUNCTION("""COMPUTED_VALUE"""),"Unidad 6 Automatización de procesos empresariales.") -> Unidad 6 Automatización de procesos empresariales. | D34: =IFERROR(__xludf.DUMMYFUNCTION("""COMPUTED_VALUE"""),"Introducción a la automatización.") -> Introducción a la automatización. | F34: =IFERROR(__xludf.DUMMYFUNCTION("""COMPUTED_VALUE"""),"Tipos de automatizadores y caracteristicas.") -> Tipos de automatizadores y caracteristicas.
B35: =IFERROR(__xludf.DUMMYFUNCTION("""COMPUTED_VALUE"""),"Unidad 6 Automatización de procesos empresariales.") -> Unidad 6 Automatización de procesos empresariales. | D35: =IFERROR(__xludf.DUMMYFUNCTION("""COMPUTED_VALUE"""),"Introducción a la automatización.") -> Introducción a la automatización. | F35: =IFERROR(__xludf.DUMMYFUNCTION("""COMPUTED_VALUE"""),"RPA como opción a estudiar.") -> RPA como opción a estudiar.
A36: 2.2 Recursos Educativos | B36: =IFERROR(__xludf.DUMMYFUNCTION("""COMPUTED_VALUE"""),"Unidad 6 Automatización de procesos empresariales.") -> Unidad 6 Automatización de procesos empresariales. | D36: =IFERROR(__xludf.DUMMYFUNCTION("""COMPUTED_VALUE"""),"Introducción a la automatización.") -> Introducción a la automatización. | F36: =IFERROR(__xludf.DUMMYFUNCTION("""COMPUTED_VALUE"""),"Ventajas y desventajas, desafios del RPA (ROI)") -> Ventajas y desventajas, desafios del RPA (ROI)
B37: =IFERROR(__xludf.DUMMYFUNCTION("""COMPUTED_VALUE"""),"Unidad 6 Automatización de procesos empresariales.") -> Unidad 6 Automatización de procesos empresariales. | D37: =IFERROR(__xludf.DUMMYFUNCTION("""COMPUTED_VALUE"""),"Introducción a la automatización.") -> Introducción a la automatización. | F37: =IFERROR(__xludf.DUMMYFUNCTION("""COMPUTED_VALUE"""),"Que es ROI y como se calcula.") -> Que es ROI y como se calcula.
A38: Tipo de Recurso a utilizar | B38: Tipo | C38: Rango Aproximando | D38: Tiempo Aproximado
A39: Presentacion | B39: Obligatorio
A40: Video | B40: Obligatorio | C40: 3 a 6 minutos
A41: Lectura | B41: Optativo
A42: Ejercicio Demostrativo | B42: Obligatorio
A44: 3. Área de Habilidades (Saber Hacer) | G44: Tiempo Aproximado | H44: 20
G45: Tiene que estar en un rango de 30 a 50 minutos
A46: Actividad 1 (Obligatoria)
A47: Competencia que predomina en la actividad | B47: Crea ..
A48: Tipo de Actividad | B48: actividades
A49: Ponderación | B49: 0
A50: Tiempo Aproximado | B50: 0
A51: Coloca el tiempo que usar en la actividad, un tiempo sugerido 30 minutos
A52: Descripcion de la Actividad
A53: Demostracion de las herramientas y normativos aplicados en escenarios reales
A57: Actividad 2 (Optativa puedes hacerla si lo consideras apropiado)
A58: Competencia que predomina en la actividad
A59: Tipo de Actividad
A60: Ponderación
A61: Tiempo Aproximado
A62: Coloca el tiempo que usar en la actividad, un tiempo sugerido 20 minutos
A63: Descripcion de la Actividad
A68: 3. Cierre | G68: Tiempo Aproximado | H68: 20
G69: Tiene que estar en un rango de 10 a 15 minutos
A70: Tiempo Aproximado
A71: Asignacion de Actividades
A72: conclusiones, recomendaciones y recordatorios de actividades
A74: Resuelve alguna duda, asigna las actividades que deben realizar, dudas de proyectos, etc

Sheet S.10
B2: Diseño de la Sesión de Laboratorio
B4: Curso | C4: ='Diseño'!C4 -> 787 - Sistemas Organizacionales y Gerenciales 2
B5: Semana | C5: 10
B6: Tiempo | C6: =H10+H21+H44+H68 -> 110
B7: Ponderación | C7: =B49+B60 -> 0
B8: Validación de Tiempo | C8: =IF(H44<=0, "❌ ERROR: La Actividad 1 debe tener un tiempo mayor a 0.", IF(H21>60, "❌ ERROR: El 'Área de Conocimiento' no puede exceder los 60 min.", IF((H10+H21+H44)<100, "❌ ERROR: El tiempo total debe ser de al menos 100 min.", "✅ VALIDACIÓN CORRECTA"))) -> ❌ ERROR: El tiempo total debe ser de al menos 100 min.
A10: 1. Área Actitudinal (Saber Ser) | G10: Tiempo Aproximado | H10: 10
G11: Tiene que estar en un rango de 3 a 5 minutos
A12: Nombre del Valor | B12: Responsabilidad
A13: Tiempo Aproximado
A14: Descripcion
A15: Implica asegurar que las implementaciones sean éticas, seguras y alineadas con los objetivos organizacionales.
A17: Como se relaciona con los conocimientos de la sesion y se aplicaria
A18: Para el estudiante, representa el compromiso de aplicar correctamente las tecnologías RPA, protegiendo la integridad de los datos y considerando el impacto en personas y procesos. Este valor fortalece su formación profesional y ética durante el semestre.
A21: 2. Área Conocimiento (Saber) | G21: Tiempo Aproximado | H21: 60
G22: No puede exceder los 60 minutos
A23: Competencia a desarrollar
A24: Competencia a desarrollar
A26: 2.1 Contenido
A27: No. | B27: Unidad | D27: Tema | F27: Sub Tema
A28: 1 | B28: =IFERROR(__xludf.DUMMYFUNCTION("FILTER('Diseño'!D:D,'Diseño'!H:H=$C$5)"),"Unidad 6 Automatización de procesos empresariales.") -> Unidad 6 Automatización de procesos empresariales. | D28: =IFERROR(__xludf.DUMMYFUNCTION("FILTER('Diseño'!E:E,'Diseño'!H:H=$C$5)"),"RPA e introducción al marketing digital") -> RPA e introducción al marketing digital | F28: =IFERROR(__xludf.DUMMYFUNCTION("FILTER('Diseño'!F:F,'Diseño'!H:H=$C$5)"),"Herramientas tecnológicas RPA") -> Herramientas tecnológicas RPA
A29: 2 | B29: =IFERROR(__xludf.DUMMYFUNCTION("""COMPUTED_VALUE"""),"Unidad 6 Automatización de procesos empresariales.") -> Unidad 6 Automatización de procesos empresariales. | D29: =IFERROR(__xludf.DUMMYFUNCTION("""COMPUTED_VALUE"""),"RPA e introducción al marketing digital") -> RPA e introducción al marketing digital | F29: =IFERROR(__xludf.DUMMYFUNCTION("""COMPUTED_VALUE"""),"Tipos y caracteristicas de las herramientas a estudiar.") -> Tipos y caracteristicas de las herramientas a estudiar.
A30: 3 | B30: =IFERROR(__xludf.DUMMYFUNCTION("""COMPUTED_VALUE"""),"Unidad 6 Automatización de procesos empresariales.") -> Unidad 6 Automatización de procesos empresariales. | D30: =IFERROR(__xludf.DUMMYFUNCTION("""COMPUTED_VALUE"""),"RPA e introducción al marketing digital") -> RPA e introducción al marketing digital | F30: =IFERROR(__xludf.DUMMYFUNCTION("""COMPUTED_VALUE"""),"Conceptos de ética y seguridad en proyectos RPA.") -> Conceptos de ética y seguridad en proyectos RPA.
A31: 4 | B31: =IFERROR(__xludf.DUMMYFUNCTION("""COMPUTED_VALUE"""),"Unidad 6 Automatización de procesos empresariales.") -> Unidad 6 Automatización de procesos empresariales. | D31: =IFERROR(__xludf.DUMMYFUNCTION("""COMPUTED_VALUE"""),"RPA e introducción al marketing digital") -> RPA e introducción al marketing digital | F31: =IFERROR(__xludf.DUMMYFUNCTION("""COMPUTED_VALUE"""),"Ejemplos de RPA") -> Ejemplos de RPA
A32: 5 | B32: =IFERROR(__xludf.DUMMYFUNCTION("""COMPUTED_VALUE"""),"Unidad 6 Automatización de procesos empresariales.") -> Unidad 6 Automatización de procesos empresariales. | D32: =IFERROR(__xludf.DUMMYFUNCTION("""COMPUTED_VALUE"""),"RPA e introducción al marketing digital") -> RPA e introducción al marketing digital | F32: =IFERROR(__xludf.DUMMYFUNCTION("""COMPUTED_VALUE"""),"Introducción a marketing digital.") -> Introducción a marketing digital.
A33: 6 | B33: =IFERROR(__xludf.DUMMYFUNCTION("""COMPUTED_VALUE"""),"Unidad 6 Automatización de procesos empresariales.") -> Unidad 6 Automatización de procesos empresariales. | D33: =IFERROR(__xludf.DUMMYFUNCTION("""COMPUTED_VALUE"""),"RPA e introducción al marketing digital") -> RPA e introducción al marketing digital | F33: =IFERROR(__xludf.DUMMYFUNCTION("""COMPUTED_VALUE"""),"Herramientas de análisis y medición.") -> Herramientas de análisis y medición.
A34: 7 | B34: =IFERROR(__xludf.DUMMYFUNCTION("""COMPUTED_VALUE"""),"Unidad 6 Automatización de procesos empresariales.") -> Unidad 6 Automatización de procesos empresariales. | D34: =IFERROR(__xludf.DUMMYFUNCTION("""COMPUTED_VALUE"""),"RPA e introducción al marketing digital") -> RPA e introducción al marketing digital | F34: =IFERROR(__xludf.DUMMYFUNCTION("""COMPUTED_VALUE"""),"Estratégias de marketing.") -> Estratégias de marketing.
B35: =IFERROR(__xludf.DUMMYFUNCTION("""COMPUTED_VALUE"""),"Unidad 7 Marketing") -> Unidad 7 Marketing | D35: =IFERROR(__xludf.DUMMYFUNCTION("""COMPUTED_VALUE"""),"Técnicas y herramientas de segmentación de mercado, tipos de analisis de datos.") -> Técnicas y herramientas de segmentación de mercado, tipos de analisis de datos. | F35: =IFERROR(__xludf.DUMMYFUNCTION("""COMPUTED_VALUE"""),"Tipos de analisis de datos y métricas.") -> Tipos de analisis de datos y métricas.
A36: 2.2 Recursos Educativos
A38: Tipo de Recurso a utilizar | B38: Tipo | C38: Rango Aproximando | D38: Tiempo Aproximado
A39: Presentacion | B39: Obligatorio
A40: Video | B40: Obligatorio | C40: 3 a 6 minutos
A41: Lectura | B41: Optativo
A42: Ejercicio Demostrativo | B42: Obligatorio
A44: 3. Área de Habilidades (Saber Hacer) | G44: Tiempo Aproximado | H44: 20
G45: Tiene que estar en un rango de 30 a 50 minutos
A46: Actividad 1 (Obligatoria)
A47: Competencia que predomina en la actividad | B47: Crea ..
A48: Tipo de Actividad | B48: actividades
A49: Ponderación | B49: 0
A50: Tiempo Aproximado | B50: 0
A51: Coloca el tiempo que usar en la actividad, un tiempo sugerido 30 minutos
A52: Descripcion de la Actividad
A53: Demostracion de las herramientas y normativos aplicados en escenarios reales
A57: Actividad 2 (Optativa puedes hacerla si lo consideras apropiado)
A58: Competencia que predomina en la actividad
A59: Tipo de Actividad
A60: Ponderación
A61: Tiempo Aproximado
A62: Coloca el tiempo que usar en la actividad, un tiempo sugerido 20 minutos
A63: Descripcion de la Actividad
A68: 3. Cierre | G68: Tiempo Aproximado | H68: 20
G69: Tiene que estar en un rango de 10 a 15 minutos
A70: Tiempo Aproximado
A71: Asignacion de Actividades
A72: conclusiones, recomendaciones y recordatorios de actividades
A74: Resuelve alguna duda, asigna las actividades que deben realizar, dudas de proyectos, etc

Sheet S.11
B2: Diseño de la Sesión de Laboratorio
B4: Curso | C4: ='Diseño'!C4 -> 787 - Sistemas Organizacionales y Gerenciales 2
B5: Semana | C5: 11
B6: Tiempo | C6: =H10+H21+H44+H68 -> 110
B7: Ponderación | C7: =B49+B60 -> 0
B8: Validación de Tiempo | C8: =IF(H44<=0, "❌ ERROR: La Actividad 1 debe tener un tiempo mayor a 0.", IF(H21>60, "❌ ERROR: El 'Área de Conocimiento' no puede exceder los 60 min.", IF((H10+H21+H44)<100, "❌ ERROR: El tiempo total debe ser de al menos 100 min.", "✅ VALIDACIÓN CORRECTA"))) -> ❌ ERROR: El tiempo total debe ser de al menos 100 min.
A10: 1. Área Actitudinal (Saber Ser) | G10: Tiempo Aproximado | H10: 10
G11: Tiene que estar en un rango de 3 a 5 minutos
A12: Nombre del Valor | B12: Honestidad
A13: Tiempo Aproximado
A14: Descripcion
A15: Este valor invita al estudiante a cerrar su formación con integridad, promoviendo una comunicación veraz, transparente y respetuosa.
A17: Como se relaciona con los conocimientos de la sesion y se aplicaria
A18: Fomentar la honestidad permite construir relaciones duraderas con el cliente y proyectar una imagen profesional ética en cualquier entorno empresarial.
A21: 2. Área Conocimiento (Saber) | G21: Tiempo Aproximado | H21: 60
G22: No puede exceder los 60 minutos
A23: Competencia a desarrollar
A24: Competencia a desarrollar
A26: 2.1 Contenido
A27: No. | B27: Unidad | D27: Tema | F27: Sub Tema
A28: 1 | B28: =IFERROR(__xludf.DUMMYFUNCTION("FILTER('Diseño'!D:D,'Diseño'!H:H=$C$5)"),"Unidad 7 Marketing") -> Unidad 7 Marketing | D28: =IFERROR(__xludf.DUMMYFUNCTION("FILTER('Diseño'!E:E,'Diseño'!H:H=$C$5)"),"Técnicas y herramientas de segmentación de mercado, tipos de analisis de datos.") -> Técnicas y herramientas de segmentación de mercado, tipos de analisis de datos. | F28: =IFERROR(__xludf.DUMMYFUNCTION("FILTER('Diseño'!F:F,'Diseño'!H:H=$C$5)"),"Herramientas de gestión y automatización") -> Herramientas de gestión y automatización
A29: 2 | B29: =IFERROR(__xludf.DUMMYFUNCTION("""COMPUTED_VALUE"""),"Unidad 7 Marketing") -> Unidad 7 Marketing | D29: =IFERROR(__xludf.DUMMYFUNCTION("""COMPUTED_VALUE"""),"Técnicas y herramientas de segmentación de mercado, tipos de analisis de datos.") -> Técnicas y herramientas de segmentación de mercado, tipos de analisis de datos. | F29: =IFERROR(__xludf.DUMMYFUNCTION("""COMPUTED_VALUE"""),"Segmentación del mercado") -> Segmentación del mercado
A30: 3 | B30: =IFERROR(__xludf.DUMMYFUNCTION("""COMPUTED_VALUE"""),"Unidad 7 Marketing") -> Unidad 7 Marketing | D30: =IFERROR(__xludf.DUMMYFUNCTION("""COMPUTED_VALUE"""),"Técnicas y herramientas de segmentación de mercado, tipos de analisis de datos.") -> Técnicas y herramientas de segmentación de mercado, tipos de analisis de datos. | F30: =IFERROR(__xludf.DUMMYFUNCTION("""COMPUTED_VALUE"""),"Analisis en la creación de campañas") -> Analisis en la creación de campañas
A31: 4 | B31: =IFERROR(__xludf.DUMMYFUNCTION("""COMPUTED_VALUE"""),"Unidad 7 Marketing") -> Unidad 7 Marketing | D31: =IFERROR(__xludf.DUMMYFUNCTION("""COMPUTED_VALUE"""),"Técnicas y herramientas de segmentación de mercado, tipos de analisis de datos.") -> Técnicas y herramientas de segmentación de mercado, tipos de analisis de datos. | F31: =IFERROR(__xludf.DUMMYFUNCTION("""COMPUTED_VALUE"""),"Herramientas de publicidad digital.") -> Herramientas de publicidad digital.
A32: 5 | B32: =IFERROR(__xludf.DUMMYFUNCTION("""COMPUTED_VALUE"""),"Unidad 7 Marketing") -> Unidad 7 Marketing | D32: =IFERROR(__xludf.DUMMYFUNCTION("""COMPUTED_VALUE"""),"Técnicas y herramientas de segmentación de mercado, tipos de analisis de datos.") -> Técnicas y herramientas de segmentación de mercado, tipos de analisis de datos. | F32: =IFERROR(__xludf.DUMMYFUNCTION("""COMPUTED_VALUE"""),"Conceptos y herramientas.") -> Conceptos y herramientas.
A33: 6 | B33: =IFERROR(__xludf.DUMMYFUNCTION("""COMPUTED_VALUE"""),"Unidad 7 Marketing") -> Unidad 7 Marketing | D33: =IFERROR(__xludf.DUMMYFUNCTION("""COMPUTED_VALUE"""),"Técnicas y herramientas de segmentación de mercado, tipos de analisis de datos.") -> Técnicas y herramientas de segmentación de mercado, tipos de analisis de datos. | F33: =IFERROR(__xludf.DUMMYFUNCTION("""COMPUTED_VALUE"""),"Estudio de técnicas, medición y optimización.") -> Estudio de técnicas, medición y optimización.
A34: 7
A36: 2.2 Recursos Educativos
A38: Tipo de Recurso a utilizar | B38: Tipo | C38: Rango Aproximando | D38: Tiempo Aproximado
A39: Presentacion | B39: Obligatorio
A40: Video | B40: Obligatorio | C40: 3 a 6 minutos
A41: Lectura | B41: Optativo
A42: Ejercicio Demostrativo | B42: Obligatorio
A44: 3. Área de Habilidades (Saber Hacer) | G44: Tiempo Aproximado | H44: 20
G45: Tiene que estar en un rango de 30 a 50 minutos
A46: Actividad 1 (Obligatoria)
A47: Competencia que predomina en la actividad | B47: Crea ..
A48: Tipo de Actividad | B48: Ejercicio practico
A49: Ponderación | B49: 0
A50: Tiempo Aproximado | B50: 0
A51: Coloca el tiempo que usar en la actividad, un tiempo sugerido 30 minutos
A52: Descripcion de la Actividad
A53: Demostracion de las herramientas y normativos aplicados en escenarios reales
A57: Actividad 2 (Optativa puedes hacerla si lo consideras apropiado)
A58: Competencia que predomina en la actividad
A59: Tipo de Actividad
A60: Ponderación
A61: Tiempo Aproximado
A62: Coloca el tiempo que usar en la actividad, un tiempo sugerido 20 minutos
A63: Descripcion de la Actividad
A68: 3. Cierre | G68: Tiempo Aproximado | H68: 20
G69: Tiene que estar en un rango de 10 a 15 minutos
A70: Tiempo Aproximado
A71: Asignacion de Actividades
A72: conclusiones, recomendaciones y recordatorios de actividades para el cierre del curso
A74: Resuelve alguna duda, asigna las actividades que deben realizar, dudas de proyectos, etc

Sheet Proyectos
B2: Proyectos
B4: Curso | C4: ='Diseño'!C4 -> 787 - Sistemas Organizacionales y Gerenciales 2
B5: Tiempo | C5: =H9+H26+H43 -> 30
B6: Ponderación | C6: =F9+F26+F43 -> 35
B7: La sumatoria de los puntos de los proyectos debe superar el 70% del total de la nota, no puede ser un 100%
A9: 1. Primer Proyecto | E9: Ponderación | F9: 35 | G9: Horas para realizarlo | H9: 30
A10: Obligatorio
A11: Competencia a desarrollar | B11: Crea propuestas de solución innovadoras utilizando metodologías de diseño estratégico en escenarios empresariales simulados de alta complejidad
A12: Competencia a desarrollar | B12: Comprende los fundamentos de la gestión gerencial aplicando teorías administrativas y de liderazgo en el análisis de casos organizacionales
A13: Competencia a desarrollar | B13: Razona procesos de negocio y el uso de algoritmos para la toma de desciones y mapear los procesos utilizando la informacion disponible y herramientas para generar flujos de trabajo y tomar desiciones en base a datos historicos y optimizar procesos
A14: Titulo | B14: Proyecto único
A15: Qué tecnologías, lenguajes de programación, plataformas, hardware o software se utilizaran
A16: Odoo, google analytics, UiPath, power BI, Base de datos relacional
A19: Descripción de lo que se realizara
A20: Un ejercicio para utilizar un CRM y ERP donde se pueda tomar datos y analizarlos con ayuda de google analitycs. Con los datos analizados presentar informes y marketing que se pueda utilizar. Tambien dashboards en power BI. Así mismo utilizar herramientas de automatización para tareas comunes y repetitivas
A26: 2. Segundo Proyecto | E26: Ponderación | G26: Horas para realizarlo
A27: Obligatorio
A28: Competencia a desarrollar
A29: Competencia a desarrollar
A30: Competencia a desarrollar
A31: Titulo
A32: Qué tecnologías, lenguajes de programación, plataformas, hardware o software se utilizaran
A36: Descripción de lo que se realizara
A43: 3. Tercer Proyecto | E43: Ponderación | G43: Horas para realizarlo
A44: Optativa
A45: Competencia a desarrollar
A46: Competencia a desarrollar
A47: Competencia a desarrollar
A48: Titulo
A49: Qué tecnologías, lenguajes de programación, plataformas, hardware o software se utilizaran
A53: Descripción de lo que se realizara

Sheet Practicas
B2: Practicas
B4: Curso | C4: ='Diseño'!C4 -> 787 - Sistemas Organizacionales y Gerenciales 2
B5: Tiempo | C5: 20
B6: Ponderación | C6: 15
B7: La sumatoria de los puntos de los practicas debe no debe super el 20%
A9: 1. Primera Practica | E9: Ponderación | F9: 15 | G9: Horas para realizarlo | H9: 20
A10: Obligatoria
A11: Competencia a desarrollar | B11: Analiza oportunidades críticas y de gran valor en un entorno empresarial haciendo uso de matrices y arboles de decisión, así como herramientas para el análisis de datos para definir la mejor planificación y dirección empresarial
A12: Competencia a desarrollar | B12: Evalúa la efectividad de procesos administrativos aplicando el ciclo del proceso administrativo para identificar áreas de mejora en la gestión organizacional y proponer acciones correctivas
A13: Competencia a desarrollar
A14: Titulo | B14: Análisis de datos e interpretación de los resultados
A15: Qué tecnologías, lenguajes de programación, plataformas, hardware o software se utilizaran
A16: Bases de Datos en la Nube, SQL, Power BI, R, Power Point,Python
A19: Descripción de lo que se realizara
A20: Realizar un ejercicio práctico de análisis de datos dentro de una organización, reconocer insights derivados del análisis, identificar y tomar las mejores decisiones estratégicas, evaluar y mejorar la eficiencia operativa y aumentar la ventaja competitiva en el mercado.
A26: 2. Segunda Practica | E26: Ponderación | G26: Horas para realizarlo
A27: Optativa
A28: Competencia a desarrollar
A29: Competencia a desarrollar
A30: Competencia a desarrollar
A31: Titulo
A32: Qué tecnologías, lenguajes de programación, plataformas, hardware o software se utilizaran
A36: Descripción de lo que se realizara
A43: 3. Tercera Practica | E43: Ponderación | G43: Horas para realizarlo
A44: Optativa
A45: Competencia a desarrollar
A46: Competencia a desarrollar
A47: Competencia a desarrollar
A48: Titulo
A49: Qué tecnologías, lenguajes de programación, plataformas, hardware o software se utilizaran
A53: Descripción de lo que se realizara
A60: 4. Cuarta Practica | E60: Ponderación | G60: Horas para realizarlo
A61: Optativa
A62: Competencia a desarrollar
A63: Competencia a desarrollar
A64: Competencia a desarrollar
A65: Titulo
A66: Qué tecnologías, lenguajes de programación, plataformas, hardware o software se utilizaran
A70: Descripción de lo que se realizara
A77: 5. Quinta Practica | E77: Ponderación | G77: Horas para realizarlo
A78: Optativa
A79: Competencia a desarrollar
A80: Competencia a desarrollar
A81: Competencia a desarrollar
A82: Titulo
A83: Qué tecnologías, lenguajes de programación, plataformas, hardware o software se utilizaran
A87: Descripción de lo que se realizara
A94: 6. Sexta Practica | E94: Ponderación | G94: Horas para realizarlo
A95: Optativa
A96: Competencia a desarrollar
A97: Competencia a desarrollar
A98: Competencia a desarrollar
A99: Titulo
A100: Qué tecnologías, lenguajes de programación, plataformas, hardware o software se utilizaran
A104: Descripción de lo que se realizara
A111: 7. Septima Practica | E111: Ponderación | G111: Horas para realizarlo
A112: Optativa
A113: Competencia a desarrollar
A114: Competencia a desarrollar
A115: Competencia a desarrollar
A116: Titulo
A117: Qué tecnologías, lenguajes de programación, plataformas, hardware o software se utilizaran
A121: Descripción de lo que se realizara

Sheet Tareas
B2: Tareas
B4: Curso | C4: ='Diseño'!C4 -> 787 - Sistemas Organizacionales y Gerenciales 2
B5: Tiempo | C5: =H9+H26+H43+H60+H77+H94+H111 -> 9
B6: Ponderación | C6: =F9+F26+F43+F60+F77+F94+F111 -> 20
B7: La sumatoria de los puntos de los practicas debe no debe super el 20% de la nota
A9: 1. Primera Tarea | E9: Ponderación | F9: 5 | G9: Horas para realizarlo | H9: 2
A10: Obligatoria
A11: Competencia a desarrollar | B11: Razona procesos de negocio y el uso de algoritmos para la toma de desciones y mapear los procesos utilizando la informacion disponible y herramientas para generar flujos de trabajo y tomar desiciones en base a datos historicos y optimizar procesos
A12: Competencia a desarrollar | B12: Recuerda conceptos fundamentales de la administración gerencial realizando la apropiada inteligencia de negos}cios y envontrar brechas para la expansion empresarial y asi lograr los obejtivos que se planificaron desde el principio
A13: Competencia a desarrollar
A14: Titulo
A15: Qué tecnologías, lenguajes de programación, plataformas, hardware o software se utilizaran
A16: Analisis, Plantilla de Planificación
A19: Descripción de lo que se realizara
A20: Plan Etrategico de transformación Tecnologia, se debe realizar una planifiacion para la correcta implementacion de un ERP y CRM
A26: 2. Segunda Tarea | E26: Ponderación | F26: 5 | G26: Horas para realizarlo | H26: 3
A27: Obligatoria
A28: Competencia a desarrollar | B28: Razona procesos de negocio y el uso de algoritmos para la toma de desciones y mapear los procesos utilizando la informacion disponible y herramientas para generar flujos de trabajo y tomar desiciones en base a datos historicos y optimizar procesos
A29: Competencia a desarrollar | B29: Recuerda conceptos fundamentales de la administración gerencial realizando la apropiada inteligencia de negos}cios y envontrar brechas para la expansion empresarial y asi lograr los obejtivos que se planificaron desde el principio
A30: Competencia a desarrollar
A31: Titulo
A32: Qué tecnologías, lenguajes de programación, plataformas, hardware o software se utilizaran
A33: MySQL, Python, R, Power BI
A36: Descripción de lo que se realizara
A37: De una Muestra de Datos de datos destructurados, deben manipular y estructurar la data, y generar 5 graficos de las tendencias encontradas, y generar una conclusion alrespecto de manera analitica
A43: 3. Tercera Tarea | E43: Ponderación | F43: 5 | G43: Horas para realizarlo | H43: 3
A44: Optativa
A45: Competencia a desarrollar | B45: Comprende los fundamentos de la gestión gerencial aplicando teorías administrativas y de liderazgo en el análisis de casos organizacionales
A46: Competencia a desarrollar | B46: Evalúa la efectividad de procesos administrativos aplicando el ciclo del proceso administrativo para identificar áreas de mejora en la gestión organizacional y proponer acciones correctivas
A47: Competencia a desarrollar
A48: Titulo
A49: Qué tecnologías, lenguajes de programación, plataformas, hardware o software se utilizaran
A50: UiPath, Gmail. Word
A53: Descripción de lo que se realizara
A54: Se debe realizar un RPA que genere documentos y los archive en la nube de Google
A60: 4. Cuarta Tarea | E60: Ponderación | F60: 5 | G60: Horas para realizarlo | H60: 1
A61: Optativa
A62: Competencia a desarrollar | B62: Crea propuestas de solución innovadoras utilizando metodologías de diseño estratégico en escenarios empresariales simulados de alta complejidad
A63: Competencia a desarrollar | B63: Recuerda conceptos fundamentales de la administración gerencial realizando la apropiada inteligencia de negos}cios y envontrar brechas para la expansion empresarial y asi lograr los obejtivos que se planificaron desde el principio
A64: Competencia a desarrollar
A65: Titulo
A66: Qué tecnologías, lenguajes de programación, plataformas, hardware o software se utilizaran
A67: Google Trends, CapCut, Meta Business Suite
A70: Descripción de lo que se realizara
A71: Diseñar una mini–campaña de marketing para un producto o servicio (real o ficticio) donde integren análisis de mercado, segmentación de clientes, propuesta de valor y canales de comunicación digital.
A77: 5. Quinta Tarea | E77: Ponderación | G77: Horas para realizarlo
A78: Optativa
A79: Competencia a desarrollar
A80: Competencia a desarrollar
A81: Competencia a desarrollar
A82: Titulo
A83: Qué tecnologías, lenguajes de programación, plataformas, hardware o software se utilizaran
A87: Descripción de lo que se realizara
A94: 6. Sexta Tarea | E94: Ponderación | G94: Horas para realizarlo
A95: Optativa
A96: Competencia a desarrollar
A97: Competencia a desarrollar
A98: Competencia a desarrollar
A99: Titulo
A100: Qué tecnologías, lenguajes de programación, plataformas, hardware o software se utilizaran
A104: Descripción de lo que se realizara
A111: 7. Septima Tarea | E111: Ponderación | G111: Horas para realizarlo
A112: Optativa
A113: Competencia a desarrollar
A114: Competencia a desarrollar
A115: Competencia a desarrollar
A116: Titulo
A117: Qué tecnologías, lenguajes de programación, plataformas, hardware o software se utilizaran
A121: Descripción de lo que se realizara

Sheet Resumen
B2: Resumen de Ponderacion y Horas para realizar las actividades
B4: Curso | C4: ='Diseño'!C4 -> 787 - Sistemas Organizacionales y Gerenciales 2
B5: Periodo al que aplica | C5: Primer Semestre 2026
B6: Total de Puntos del Laboratorio
A9: Actividades Formativas | B9: 30 | D9: Proyectos | E9: 35
A10: Debe abarcar entre el 20% y 30% de la Nota | D10: Debe abarcar entre el 60% y 70% de la Nota
A12: Tipo de Actividad | B12: Ponderacion | C12: Horas Aproximadas para realizarlo | D12: Observaciones
A13: Actividades durante el peridodo de laboratorio | B13: 30 | C13: 3 | D13: Cortos y Examen Final | E13: Sumatoria de todas las semas
A14: Proyectos | B14: =Proyectos!C6 -> 35 | C14: =Proyectos!C5 -> 30
A15: Practicas | B15: =Practicas!C6 -> 15 | C15: =Practicas!C5 -> 20
A16: Tareas | B16: =Tareas!C6 -> 20 | C16: =Tareas!C5 -> 9
A17: Total | B17: =SUM(B13:B16) -> 100 | C17: =SUM(C13:C16) -> 62

Sheet METADATA
A1: =IFERROR(__xludf.DUMMYFUNCTION("IMPORTRANGE(""1j2lHEvOoZ_EPY086Qt7f7AFaZGVfiYKJxXlsnNfWCA0"",""Listado Cursos!H:L"")"),"Codigo-Nombre") -> Codigo-Nombre | B1: =IFERROR(__xludf.DUMMYFUNCTION("""COMPUTED_VALUE"""),"Diseño Curricular V01") -> Diseño Curricular V01 | C1: =IFERROR(__xludf.DUMMYFUNCTION("""COMPUTED_VALUE"""),"Analisis de Contexto V01") -> Analisis de Contexto V01 | D1: =IFERROR(__xludf.DUMMYFUNCTION("""COMPUTED_VALUE"""),"2_Analisis_Internacional_y_Local") -> 2_Analisis_Internacional_y_Local | E1: =IFERROR(__xludf.DUMMYFUNCTION("""COMPUTED_VALUE"""),"3_Diseño_Curricular") -> 3_Diseño_Curricular | H1: =IFERROR(__xludf.DUMMYFUNCTION("IMPORTRANGE(VLOOKUP('Diseño'!C4,A:E,4,FALSE), ""Competencias_1re_Sem_2026!B10:J23"")"),1.0) -> 1 | I1: =IFERROR(__xludf.DUMMYFUNCTION("""COMPUTED_VALUE"""),"General") -> General | J1: =IFERROR(__xludf.DUMMYFUNCTION("""COMPUTED_VALUE"""),"Analiza") -> Analiza | K1: =IFERROR(__xludf.DUMMYFUNCTION("""COMPUTED_VALUE"""),"oportunidades críticas y de gran valor en un entorno empresarial") -> oportunidades críticas y de gran valor en un entorno empresarial | M1: =IFERROR(__xludf.DUMMYFUNCTION("""COMPUTED_VALUE"""),"haciendo uso de matrices y arboles de decisión, así como herramientas para el análisis de datos") -> haciendo uso de matrices y arboles de decisión, así como herramientas para el análisis de datos | N1: =IFERROR(__xludf.DUMMYFUNCTION("""COMPUTED_VALUE"""),"para definir la mejor planificación y dirección empresarial ") -> para definir la mejor planificación y dirección empresarial | P1: =IFERROR(__xludf.DUMMYFUNCTION("""COMPUTED_VALUE"""),"Recordar") -> Recordar
A2: =IFERROR(__xludf.DUMMYFUNCTION("""COMPUTED_VALUE"""),"17 - Área Social Humanística 1") -> 17 - Área Social Humanística 1 | I2: =IFERROR(__xludf.DUMMYFUNCTION("""COMPUTED_VALUE"""),"Analiza oportunidades críticas y de gran valor en un entorno empresarial haciendo uso de matrices y arboles de decisión, así como herramientas para el análisis de datos para definir la mejor planificación y dirección empresarial ") -> Analiza oportunidades críticas y de gran valor en un entorno empresarial haciendo uso de matrices y arboles de decisión, así como herramientas para el análisis de datos para definir la mejor planificación y dirección empresarial
A3: =IFERROR(__xludf.DUMMYFUNCTION("""COMPUTED_VALUE"""),"101 - Área Matemática Básica 1") -> 101 - Área Matemática Básica 1 | H3: =IFERROR(__xludf.DUMMYFUNCTION("""COMPUTED_VALUE"""),2.0) -> 2 | I3: =IFERROR(__xludf.DUMMYFUNCTION("""COMPUTED_VALUE"""),"General") -> General | J3: =IFERROR(__xludf.DUMMYFUNCTION("""COMPUTED_VALUE"""),"Evalúa") -> Evalúa | K3: =IFERROR(__xludf.DUMMYFUNCTION("""COMPUTED_VALUE"""),"la efectividad de procesos administrativos ") -> la efectividad de procesos administrativos | M3: =IFERROR(__xludf.DUMMYFUNCTION("""COMPUTED_VALUE"""),"aplicando el ciclo del proceso administrativo") -> aplicando el ciclo del proceso administrativo | N3: =IFERROR(__xludf.DUMMYFUNCTION("""COMPUTED_VALUE"""),"para identificar áreas de mejora en la gestión organizacional y proponer acciones correctivas ") -> para identificar áreas de mejora en la gestión organizacional y proponer acciones correctivas | P3: =IFERROR(__xludf.DUMMYFUNCTION("""COMPUTED_VALUE"""),"Evaluar") -> Evaluar
A4: =IFERROR(__xludf.DUMMYFUNCTION("""COMPUTED_VALUE"""),"5 - Técnicas de Estudio e Investigación") -> 5 - Técnicas de Estudio e Investigación | I4: =IFERROR(__xludf.DUMMYFUNCTION("""COMPUTED_VALUE"""),"Evalúa la efectividad de procesos administrativos aplicando el ciclo del proceso administrativo para identificar áreas de mejora en la gestión organizacional y proponer acciones correctivas ") -> Evalúa la efectividad de procesos administrativos aplicando el ciclo del proceso administrativo para identificar áreas de mejora en la gestión organizacional y proponer acciones correctivas
A5: =IFERROR(__xludf.DUMMYFUNCTION("""COMPUTED_VALUE"""),"39 - Deportes 1") -> 39 - Deportes 1 | H5: =IFERROR(__xludf.DUMMYFUNCTION("""COMPUTED_VALUE"""),3.0) -> 3 | I5: =IFERROR(__xludf.DUMMYFUNCTION("""COMPUTED_VALUE"""),"Especifica") -> Especifica | J5: =IFERROR(__xludf.DUMMYFUNCTION("""COMPUTED_VALUE"""),"Razona") -> Razona | K5: =IFERROR(__xludf.DUMMYFUNCTION("""COMPUTED_VALUE"""),"procesos de negocio y el uso de algoritmos para la toma de desciones y mapear los procesos ") -> procesos de negocio y el uso de algoritmos para la toma de desciones y mapear los procesos | M5: =IFERROR(__xludf.DUMMYFUNCTION("""COMPUTED_VALUE"""),"utilizando la informacion disponible y herramientas para generar flujos de trabajo") -> utilizando la informacion disponible y herramientas para generar flujos de trabajo | N5: =IFERROR(__xludf.DUMMYFUNCTION("""COMPUTED_VALUE"""),"y tomar desiciones en base a datos historicos y optimizar procesos ") -> y tomar desiciones en base a datos historicos y optimizar procesos | P5: =IFERROR(__xludf.DUMMYFUNCTION("""COMPUTED_VALUE"""),"Analizar") -> Analizar
A6: =IFERROR(__xludf.DUMMYFUNCTION("""COMPUTED_VALUE"""),"6 - Idioma Tecnico 1") -> 6 - Idioma Tecnico 1 | I6: =IFERROR(__xludf.DUMMYFUNCTION("""COMPUTED_VALUE"""),"Razona procesos de negocio y el uso de algoritmos para la toma de desciones y mapear los procesos utilizando la informacion disponible y herramientas para generar flujos de trabajo y tomar desiciones en base a datos historicos y optimizar procesos"&" ") -> Razona procesos de negocio y el uso de algoritmos para la toma de desciones y mapear los procesos utilizando la informacion disponible y herramientas para generar flujos de trabajo y tomar desiciones en base a datos historicos y optimizar procesos
A7: =IFERROR(__xludf.DUMMYFUNCTION("""COMPUTED_VALUE"""),"19 - Área Social Humanística 2") -> 19 - Área Social Humanística 2 | H7: =IFERROR(__xludf.DUMMYFUNCTION("""COMPUTED_VALUE"""),4.0) -> 4 | I7: =IFERROR(__xludf.DUMMYFUNCTION("""COMPUTED_VALUE"""),"Especifica") -> Especifica | J7: =IFERROR(__xludf.DUMMYFUNCTION("""COMPUTED_VALUE"""),"Implementa") -> Implementa | K7: =IFERROR(__xludf.DUMMYFUNCTION("""COMPUTED_VALUE"""),"utilizando Workflows para entandarizar ") -> utilizando Workflows para entandarizar | M7: =IFERROR(__xludf.DUMMYFUNCTION("""COMPUTED_VALUE"""),"utilizando Workflows para entandarizar ") -> utilizando Workflows para entandarizar | N7: =IFERROR(__xludf.DUMMYFUNCTION("""COMPUTED_VALUE"""),"los procesos de transformacion digital aplicando normas internacionales ") -> los procesos de transformacion digital aplicando normas internacionales | P7: =IFERROR(__xludf.DUMMYFUNCTION("""COMPUTED_VALUE"""),"Aplicar") -> Aplicar
A8: =IFERROR(__xludf.DUMMYFUNCTION("""COMPUTED_VALUE"""),"103 - Área Matemática Básica 2") -> 103 - Área Matemática Básica 2 | I8: =IFERROR(__xludf.DUMMYFUNCTION("""COMPUTED_VALUE"""),"Implementa utilizando Workflows para entandarizar utilizando Workflows para entandarizar los procesos de transformacion digital aplicando normas internacionales ") -> Implementa utilizando Workflows para entandarizar utilizando Workflows para entandarizar los procesos de transformacion digital aplicando normas internacionales
A9: =IFERROR(__xludf.DUMMYFUNCTION("""COMPUTED_VALUE"""),"960 - Matemática Para Computación 1") -> 960 - Matemática Para Computación 1 | H9: =IFERROR(__xludf.DUMMYFUNCTION("""COMPUTED_VALUE"""),5.0) -> 5 | I9: =IFERROR(__xludf.DUMMYFUNCTION("""COMPUTED_VALUE"""),"Especifica") -> Especifica | J9: =IFERROR(__xludf.DUMMYFUNCTION("""COMPUTED_VALUE"""),"Recuerda") -> Recuerda | K9: =IFERROR(__xludf.DUMMYFUNCTION("""COMPUTED_VALUE"""),"conceptos fundamentales de la administración gerencial") -> conceptos fundamentales de la administración gerencial | M9: =IFERROR(__xludf.DUMMYFUNCTION("""COMPUTED_VALUE"""),"realizando la apropiada inteligencia de negos}cios y envontrar brechas para la expansion empresarial") -> realizando la apropiada inteligencia de negos}cios y envontrar brechas para la expansion empresarial | N9: =IFERROR(__xludf.DUMMYFUNCTION("""COMPUTED_VALUE"""),"y asi lograr los obejtivos que se planificaron desde el principio") -> y asi lograr los obejtivos que se planificaron desde el principio | P9: =IFERROR(__xludf.DUMMYFUNCTION("""COMPUTED_VALUE"""),"Recordar") -> Recordar
A10: =IFERROR(__xludf.DUMMYFUNCTION("""COMPUTED_VALUE"""),"147 - Física Básica") -> 147 - Física Básica | I10: =IFERROR(__xludf.DUMMYFUNCTION("""COMPUTED_VALUE"""),"Recuerda conceptos fundamentales de la administración gerencial realizando la apropiada inteligencia de negos}cios y envontrar brechas para la expansion empresarial y asi lograr los obejtivos que se planificaron desde el principio ") -> Recuerda conceptos fundamentales de la administración gerencial realizando la apropiada inteligencia de negos}cios y envontrar brechas para la expansion empresarial y asi lograr los obejtivos que se planificaron desde el principio
A11: =IFERROR(__xludf.DUMMYFUNCTION("""COMPUTED_VALUE"""),"40 - Deportes 2") -> 40 - Deportes 2 | H11: =IFERROR(__xludf.DUMMYFUNCTION("""COMPUTED_VALUE"""),6.0) -> 6 | I11: =IFERROR(__xludf.DUMMYFUNCTION("""COMPUTED_VALUE"""),"Especifica") -> Especifica | J11: =IFERROR(__xludf.DUMMYFUNCTION("""COMPUTED_VALUE"""),"Crea") -> Crea | K11: =IFERROR(__xludf.DUMMYFUNCTION("""COMPUTED_VALUE"""),"propuestas de solución innovadoras") -> propuestas de solución innovadoras | M11: =IFERROR(__xludf.DUMMYFUNCTION("""COMPUTED_VALUE"""),"utilizando metodologías de diseño estratégico") -> utilizando metodologías de diseño estratégico | N11: =IFERROR(__xludf.DUMMYFUNCTION("""COMPUTED_VALUE"""),"en escenarios empresariales simulados de alta complejidad") -> en escenarios empresariales simulados de alta complejidad | P11: =IFERROR(__xludf.DUMMYFUNCTION("""COMPUTED_VALUE"""),"Crear") -> Crear
A12: =IFERROR(__xludf.DUMMYFUNCTION("""COMPUTED_VALUE"""),"8 - Idioma Técnico 2") -> 8 - Idioma Técnico 2 | I12: =IFERROR(__xludf.DUMMYFUNCTION("""COMPUTED_VALUE"""),"Crea propuestas de solución innovadoras utilizando metodologías de diseño estratégico en escenarios empresariales simulados de alta complejidad ") -> Crea propuestas de solución innovadoras utilizando metodologías de diseño estratégico en escenarios empresariales simulados de alta complejidad
A13: =IFERROR(__xludf.DUMMYFUNCTION("""COMPUTED_VALUE"""),"795 - Logica de Sitemas") -> 795 - Logica de Sitemas | B13: =IFERROR(__xludf.DUMMYFUNCTION("""COMPUTED_VALUE"""),"1tGblVNcAY7QU_u00ZUgf5GJjDZOK39vXt9FvZeMfPKg") -> 1tGblVNcAY7QU_u00ZUgf5GJjDZOK39vXt9FvZeMfPKg | C13: =IFERROR(__xludf.DUMMYFUNCTION("""COMPUTED_VALUE"""),"1olpUmnSmvTLYIIWFmjmPX_CYPTPOprpPEwh7xMvm2WM") -> 1olpUmnSmvTLYIIWFmjmPX_CYPTPOprpPEwh7xMvm2WM | D13: =IFERROR(__xludf.DUMMYFUNCTION("""COMPUTED_VALUE"""),"17agcDtIQgmVILM9RXVaUBYkv_J7pJleLEkxEkIyMJJM") -> 17agcDtIQgmVILM9RXVaUBYkv_J7pJleLEkxEkIyMJJM | E13: =IFERROR(__xludf.DUMMYFUNCTION("""COMPUTED_VALUE"""),"1w95w-5-FomsEx4h6E_6QIaFvwjWn3GpS") -> 1w95w-5-FomsEx4h6E_6QIaFvwjWn3GpS | H13: =IFERROR(__xludf.DUMMYFUNCTION("""COMPUTED_VALUE"""),7.0) -> 7 | I13: =IFERROR(__xludf.DUMMYFUNCTION("""COMPUTED_VALUE"""),"Especifica") -> Especifica | J13: =IFERROR(__xludf.DUMMYFUNCTION("""COMPUTED_VALUE"""),"Comprende") -> Comprende | K13: =IFERROR(__xludf.DUMMYFUNCTION("""COMPUTED_VALUE"""),"los fundamentos de la gestión gerencial") -> los fundamentos de la gestión gerencial | M13: =IFERROR(__xludf.DUMMYFUNCTION("""COMPUTED_VALUE"""),"aplicando teorías administrativas y de liderazgo") -> aplicando teorías administrativas y de liderazgo | N13: =IFERROR(__xludf.DUMMYFUNCTION("""COMPUTED_VALUE"""),"en el análisis de casos organizacionales") -> en el análisis de casos organizacionales | P13: =IFERROR(__xludf.DUMMYFUNCTION("""COMPUTED_VALUE"""),"Comprender") -> Comprender
A14: =IFERROR(__xludf.DUMMYFUNCTION("""COMPUTED_VALUE"""),"962 - Matemática Para Computación 2") -> 962 - Matemática Para Computación 2 | I14: =IFERROR(__xludf.DUMMYFUNCTION("""COMPUTED_VALUE"""),"Comprende los fundamentos de la gestión gerencial aplicando teorías administrativas y de liderazgo en el análisis de casos organizacionales ") -> Comprende los fundamentos de la gestión gerencial aplicando teorías administrativas y de liderazgo en el análisis de casos organizacionales
A15: =IFERROR(__xludf.DUMMYFUNCTION("""COMPUTED_VALUE"""),"770 - Introducción a ala programación y computación 1") -> 770 - Introducción a ala programación y computación 1 | B15: =IFERROR(__xludf.DUMMYFUNCTION("""COMPUTED_VALUE"""),"1hnCz3e7R539DMJA_6KBromYXyQWjR5cbX4eUFYyZB78") -> 1hnCz3e7R539DMJA_6KBromYXyQWjR5cbX4eUFYyZB78 | C15: =IFERROR(__xludf.DUMMYFUNCTION("""COMPUTED_VALUE"""),"13K0AQ2QyRJmkDL_B9YKTYVy3OKQyLCIBTe0sAqstrFI") -> 13K0AQ2QyRJmkDL_B9YKTYVy3OKQyLCIBTe0sAqstrFI | D15: =IFERROR(__xludf.DUMMYFUNCTION("""COMPUTED_VALUE"""),"1kT0U-6N_PfLXHZnMI7r4DBtAi8DedDHU4nlc6LJYNo0") -> 1kT0U-6N_PfLXHZnMI7r4DBtAi8DedDHU4nlc6LJYNo0 | E15: =IFERROR(__xludf.DUMMYFUNCTION("""COMPUTED_VALUE"""),"1ckY3kIc3clzV4xpXc56uv8KpfX4YxL-8") -> 1ckY3kIc3clzV4xpXc56uv8KpfX4YxL-8
A16: =IFERROR(__xludf.DUMMYFUNCTION("""COMPUTED_VALUE"""),"107 - Área Matemática Intermedia 1") -> 107 - Área Matemática Intermedia 1
A17: =IFERROR(__xludf.DUMMYFUNCTION("""COMPUTED_VALUE"""),"150 - Fisica 1") -> 150 - Fisica 1 | I17: =I2 -> Analiza oportunidades críticas y de gran valor en un entorno empresarial haciendo uso de matrices y arboles de decisión, así como herramientas para el análisis de datos para definir la mejor planificación y dirección empresarial
A18: =IFERROR(__xludf.DUMMYFUNCTION("""COMPUTED_VALUE"""),"1 - Ética Profesional") -> 1 - Ética Profesional | I18: =I4 -> Evalúa la efectividad de procesos administrativos aplicando el ciclo del proceso administrativo para identificar áreas de mejora en la gestión organizacional y proponer acciones correctivas
A19: =IFERROR(__xludf.DUMMYFUNCTION("""COMPUTED_VALUE"""),"9 - Idioma Técnico 3") -> 9 - Idioma Técnico 3 | I19: =I6 -> Razona procesos de negocio y el uso de algoritmos para la toma de desciones y mapear los procesos utilizando la informacion disponible y herramientas para generar flujos de trabajo y tomar desiciones en base a datos historicos y optimizar procesos
A20: =IFERROR(__xludf.DUMMYFUNCTION("""COMPUTED_VALUE"""),"796 - Lenguajes Formales y de Programación") -> 796 - Lenguajes Formales y de Programación | B20: =IFERROR(__xludf.DUMMYFUNCTION("""COMPUTED_VALUE"""),"1-dPQ2ZCWWgBi4gyaV8KmnDWxF063I-zfJutKPMwJjrw") -> 1-dPQ2ZCWWgBi4gyaV8KmnDWxF063I-zfJutKPMwJjrw | C20: =IFERROR(__xludf.DUMMYFUNCTION("""COMPUTED_VALUE"""),"14p5IrzE6q20i9mtWRrbgJgIQTyfVIS4RiO1JbrFY3Ng") -> 14p5IrzE6q20i9mtWRrbgJgIQTyfVIS4RiO1JbrFY3Ng | D20: =IFERROR(__xludf.DUMMYFUNCTION("""COMPUTED_VALUE"""),"1AGg7thSM78QT3j-XZKX-5O8_jS800m3f69bnsKDL7lw") -> 1AGg7thSM78QT3j-XZKX-5O8_jS800m3f69bnsKDL7lw | E20: =IFERROR(__xludf.DUMMYFUNCTION("""COMPUTED_VALUE"""),"1OmnbU2f0aXljqhgz4fTmiAjtEt-JJYai") -> 1OmnbU2f0aXljqhgz4fTmiAjtEt-JJYai | I20: =I8 -> Implementa utilizando Workflows para entandarizar utilizando Workflows para entandarizar los procesos de transformacion digital aplicando normas internacionales
A21: =IFERROR(__xludf.DUMMYFUNCTION("""COMPUTED_VALUE"""),"771 - Introducción a la Programación y Computación 2") -> 771 - Introducción a la Programación y Computación 2 | B21: =IFERROR(__xludf.DUMMYFUNCTION("""COMPUTED_VALUE"""),"1__RmanO4MiKBpppCFzGzdDC2fWb5cD2m02xjOur_6nk") -> 1__RmanO4MiKBpppCFzGzdDC2fWb5cD2m02xjOur_6nk | C21: =IFERROR(__xludf.DUMMYFUNCTION("""COMPUTED_VALUE"""),"1hwyEeHtTnYmAXwVixwCmwcQ_1S6x1ID8qghxNj_2les") -> 1hwyEeHtTnYmAXwVixwCmwcQ_1S6x1ID8qghxNj_2les | D21: =IFERROR(__xludf.DUMMYFUNCTION("""COMPUTED_VALUE"""),"1u-w0HNCWqujufP7pN3mFHcpWgitZrec1rkML6inpQK4") -> 1u-w0HNCWqujufP7pN3mFHcpWgitZrec1rkML6inpQK4 | E21: =IFERROR(__xludf.DUMMYFUNCTION("""COMPUTED_VALUE"""),"1cHaBQxjzhcYUkXb4b-PtA5PT2axoYWIL") -> 1cHaBQxjzhcYUkXb4b-PtA5PT2axoYWIL | I21: =I10 -> Recuerda conceptos fundamentales de la administración gerencial realizando la apropiada inteligencia de negos}cios y envontrar brechas para la expansion empresarial y asi lograr los obejtivos que se planificaron desde el principio
A22: =IFERROR(__xludf.DUMMYFUNCTION("""COMPUTED_VALUE"""),"112 - Área Matemática Intermedia 2") -> 112 - Área Matemática Intermedia 2 | I22: =I12 -> Crea propuestas de solución innovadoras utilizando metodologías de diseño estratégico en escenarios empresariales simulados de alta complejidad
A23: =IFERROR(__xludf.DUMMYFUNCTION("""COMPUTED_VALUE"""),"114 - Área Matemática Intermedia 3") -> 114 - Área Matemática Intermedia 3 | I23: =I14 -> Comprende los fundamentos de la gestión gerencial aplicando teorías administrativas y de liderazgo en el análisis de casos organizacionales
A24: =IFERROR(__xludf.DUMMYFUNCTION("""COMPUTED_VALUE"""),"152 - Física 2") -> 152 - Física 2
A25: =IFERROR(__xludf.DUMMYFUNCTION("""COMPUTED_VALUE"""),"10 - Lógica") -> 10 - Lógica
A26: =IFERROR(__xludf.DUMMYFUNCTION("""COMPUTED_VALUE"""),"11 - Idioma Técnico 4") -> 11 - Idioma Técnico 4
A27: =IFERROR(__xludf.DUMMYFUNCTION("""COMPUTED_VALUE"""),"2025 - Prácticas Iniciales") -> 2025 - Prácticas Iniciales
A28: =IFERROR(__xludf.DUMMYFUNCTION("""COMPUTED_VALUE"""),"732 - Estadística 1") -> 732 - Estadística 1
A29: =IFERROR(__xludf.DUMMYFUNCTION("""COMPUTED_VALUE"""),"777 - Organización de Lenguajes y Compiladores 1") -> 777 - Organización de Lenguajes y Compiladores 1 | B29: =IFERROR(__xludf.DUMMYFUNCTION("""COMPUTED_VALUE"""),"1sMJr8kYIDF7fR6Jn6GMDZp8CdJCeGqxbVA5UTdBCrkM") -> 1sMJr8kYIDF7fR6Jn6GMDZp8CdJCeGqxbVA5UTdBCrkM | C29: =IFERROR(__xludf.DUMMYFUNCTION("""COMPUTED_VALUE"""),"1sznB5glJmAKD25Jh38PR_uvVmYLeupPdQfr5Z_cGdy0") -> 1sznB5glJmAKD25Jh38PR_uvVmYLeupPdQfr5Z_cGdy0 | D29: =IFERROR(__xludf.DUMMYFUNCTION("""COMPUTED_VALUE"""),"1kBA4IGrUYJDRe0Y1euEq_2KSZ_6qIOJf4ChyOoB7-bw") -> 1kBA4IGrUYJDRe0Y1euEq_2KSZ_6qIOJf4ChyOoB7-bw | E29: =IFERROR(__xludf.DUMMYFUNCTION("""COMPUTED_VALUE"""),"14tEUE8qfBh4CI8Qotf2UbaoJFzpnWz0r") -> 14tEUE8qfBh4CI8Qotf2UbaoJFzpnWz0r
A30: =IFERROR(__xludf.DUMMYFUNCTION("""COMPUTED_VALUE"""),"964 - Organización Computacional") -> 964 - Organización Computacional | B30: =IFERROR(__xludf.DUMMYFUNCTION("""COMPUTED_VALUE"""),"1daYmFoqU1khKZXb4p_ygv5jH4tkv8-tTjdTDSUh72F0") -> 1daYmFoqU1khKZXb4p_ygv5jH4tkv8-tTjdTDSUh72F0 | C30: =IFERROR(__xludf.DUMMYFUNCTION("""COMPUTED_VALUE"""),"1Iu2w--EUMRmqIHGvbgJsupMFeebEMTKXZFzhrwGZtOs") -> 1Iu2w--EUMRmqIHGvbgJsupMFeebEMTKXZFzhrwGZtOs | D30: =IFERROR(__xludf.DUMMYFUNCTION("""COMPUTED_VALUE"""),"1gqR4HPKEldyIGuEb4K6wpzCwLjthMqCU81C5lPPJfYo") -> 1gqR4HPKEldyIGuEb4K6wpzCwLjthMqCU81C5lPPJfYo | E30: =IFERROR(__xludf.DUMMYFUNCTION("""COMPUTED_VALUE"""),"168JiBG-dVAZLw3Z00Wh0GzOSNJ7yxpVe") -> 168JiBG-dVAZLw3Z00Wh0GzOSNJ7yxpVe
A31: =IFERROR(__xludf.DUMMYFUNCTION("""COMPUTED_VALUE"""),"772 - Estructuras de Datos") -> 772 - Estructuras de Datos | B31: =IFERROR(__xludf.DUMMYFUNCTION("""COMPUTED_VALUE"""),"1rTNY7hLmB5N26Z2z6EtF0axcaKKizdu0eLKqLiwUhto") -> 1rTNY7hLmB5N26Z2z6EtF0axcaKKizdu0eLKqLiwUhto | C31: =IFERROR(__xludf.DUMMYFUNCTION("""COMPUTED_VALUE"""),"1e8AAZ395NIODTRjmbwP3Bvdb1OJlsJawLywq7NixwcM") -> 1e8AAZ395NIODTRjmbwP3Bvdb1OJlsJawLywq7NixwcM | D31: =IFERROR(__xludf.DUMMYFUNCTION("""COMPUTED_VALUE"""),"1PVCPYoBYbA64z-ceE8HVIWfvtziNTX_CeNB1XrAFUmk") -> 1PVCPYoBYbA64z-ceE8HVIWfvtziNTX_CeNB1XrAFUmk | E31: =IFERROR(__xludf.DUMMYFUNCTION("""COMPUTED_VALUE"""),"1E0q2biUjzF_2MGRSFGlAtpUs_jiKeYCi") -> 1E0q2biUjzF_2MGRSFGlAtpUs_jiKeYCi
A32: =IFERROR(__xludf.DUMMYFUNCTION("""COMPUTED_VALUE"""),"116 - Matemática Aplicada 3") -> 116 - Matemática Aplicada 3
A33: =IFERROR(__xludf.DUMMYFUNCTION("""COMPUTED_VALUE"""),"118 - Matemática Aplicada 1") -> 118 - Matemática Aplicada 1
A34: =IFERROR(__xludf.DUMMYFUNCTION("""COMPUTED_VALUE"""),"18 - Filosofía de la Ciencia") -> 18 - Filosofía de la Ciencia
A35: =IFERROR(__xludf.DUMMYFUNCTION("""COMPUTED_VALUE"""),"722 - Teoría de Sistemas 1") -> 722 - Teoría de Sistemas 1 | B35: =IFERROR(__xludf.DUMMYFUNCTION("""COMPUTED_VALUE"""),"1npGvBttUX2JHkjnmDRQmNhZacltUudlNKCQsLV09BaU") -> 1npGvBttUX2JHkjnmDRQmNhZacltUudlNKCQsLV09BaU | C35: =IFERROR(__xludf.DUMMYFUNCTION("""COMPUTED_VALUE"""),"1hMUPf0qs2ca-iLxfgxe8cYMynK4MJCa34p7GqRHJXbE") -> 1hMUPf0qs2ca-iLxfgxe8cYMynK4MJCa34p7GqRHJXbE | D35: =IFERROR(__xludf.DUMMYFUNCTION("""COMPUTED_VALUE"""),"1ATHMFdf0XbWCqh2hcVgPbB3YAnr637GqzneY0kwZPXs") -> 1ATHMFdf0XbWCqh2hcVgPbB3YAnr637GqzneY0kwZPXs | E35: =IFERROR(__xludf.DUMMYFUNCTION("""COMPUTED_VALUE"""),"1me1nH7wLH9V0Y0D1dBAqO-cxBMvcPd1a") -> 1me1nH7wLH9V0Y0D1dBAqO-cxBMvcPd1a
A36: =IFERROR(__xludf.DUMMYFUNCTION("""COMPUTED_VALUE"""),"601 - Investigación de Operaciones 1") -> 601 - Investigación de Operaciones 1
A37: =IFERROR(__xludf.DUMMYFUNCTION("""COMPUTED_VALUE"""),"14 - Economía") -> 14 - Economía | B37: =IFERROR(__xludf.DUMMYFUNCTION("""COMPUTED_VALUE"""),"169ieOogZaXHMs_PddYQfqqWTOgqfbgT1NUf8dchmb4U") -> 169ieOogZaXHMs_PddYQfqqWTOgqfbgT1NUf8dchmb4U | C37: =IFERROR(__xludf.DUMMYFUNCTION("""COMPUTED_VALUE"""),"1aRV1pjb7CPc1NcugRe2l92I-OqNZYb_4YmhuHZtvXzs") -> 1aRV1pjb7CPc1NcugRe2l92I-OqNZYb_4YmhuHZtvXzs | D37: =IFERROR(__xludf.DUMMYFUNCTION("""COMPUTED_VALUE"""),"1pajOO3AWmOi1jPG43utDMvSL31e0t1UDzgvEQYveS28") -> 1pajOO3AWmOi1jPG43utDMvSL31e0t1UDzgvEQYveS28 | E37: =IFERROR(__xludf.DUMMYFUNCTION("""COMPUTED_VALUE"""),"1WqxKIBh1lpbr01vS0jn_ragnl3d_04zY") -> 1WqxKIBh1lpbr01vS0jn_ragnl3d_04zY
A38: =IFERROR(__xludf.DUMMYFUNCTION("""COMPUTED_VALUE"""),"781 - Organización de Lenguajes y Compiladores 2") -> 781 - Organización de Lenguajes y Compiladores 2 | B38: =IFERROR(__xludf.DUMMYFUNCTION("""COMPUTED_VALUE"""),"18dQYgiKWkpI2wogupgHf8u3PbCa0cKqMH6-ZsAIhLPw") -> 18dQYgiKWkpI2wogupgHf8u3PbCa0cKqMH6-ZsAIhLPw | C38: =IFERROR(__xludf.DUMMYFUNCTION("""COMPUTED_VALUE"""),"1FvDr2nu5sW0gxDkpPanB4sWbi78KZCAhc6wrywlrvlE") -> 1FvDr2nu5sW0gxDkpPanB4sWbi78KZCAhc6wrywlrvlE | D38: =IFERROR(__xludf.DUMMYFUNCTION("""COMPUTED_VALUE"""),"1vR-fd-_MbOLAfMSv4L0B7CMj6jdlTkOQCD95r1XcqZI") -> 1vR-fd-_MbOLAfMSv4L0B7CMj6jdlTkOQCD95r1XcqZI | E38: =IFERROR(__xludf.DUMMYFUNCTION("""COMPUTED_VALUE"""),"1OpTiDYbGu0wNKI3xw8Lxhx1c4euS0YR9") -> 1OpTiDYbGu0wNKI3xw8Lxhx1c4euS0YR9
A39: =IFERROR(__xludf.DUMMYFUNCTION("""COMPUTED_VALUE"""),"778 - Arquitectura de Computadoras y Ensambladores 1") -> 778 - Arquitectura de Computadoras y Ensambladores 1 | B39: =IFERROR(__xludf.DUMMYFUNCTION("""COMPUTED_VALUE"""),"13gNb-7XS_aMptaL1TLnLB5k06Y_okRzOgjzOxLHNuiI") -> 13gNb-7XS_aMptaL1TLnLB5k06Y_okRzOgjzOxLHNuiI | C39: =IFERROR(__xludf.DUMMYFUNCTION("""COMPUTED_VALUE"""),"1dlO25kugHQowRwF3LcOkrFuLGg-hP9mn9OW7x7GssMc") -> 1dlO25kugHQowRwF3LcOkrFuLGg-hP9mn9OW7x7GssMc | D39: =IFERROR(__xludf.DUMMYFUNCTION("""COMPUTED_VALUE"""),"1jMElka7Ve71KPvj9i1bHpM_BAVnEwEXLC-W_04LIFGg") -> 1jMElka7Ve71KPvj9i1bHpM_BAVnEwEXLC-W_04LIFGg | E39: =IFERROR(__xludf.DUMMYFUNCTION("""COMPUTED_VALUE"""),"1vPaqqtPi3QjCFIUp-K5im-qBz572iNPY") -> 1vPaqqtPi3QjCFIUp-K5im-qBz572iNPY
A40: =IFERROR(__xludf.DUMMYFUNCTION("""COMPUTED_VALUE"""),"773 - Manejo e Implementación de Archivos") -> 773 - Manejo e Implementación de Archivos | B40: =IFERROR(__xludf.DUMMYFUNCTION("""COMPUTED_VALUE"""),"1VDaIod2C3XfezxQfz50xvWZ9yVVdVvNIqd-1xbJmaD8") -> 1VDaIod2C3XfezxQfz50xvWZ9yVVdVvNIqd-1xbJmaD8 | C40: =IFERROR(__xludf.DUMMYFUNCTION("""COMPUTED_VALUE"""),"1MkqyTtzzzyQyC--twNt__AoC_Sd0UBC67j0f9nktivE") -> 1MkqyTtzzzyQyC--twNt__AoC_Sd0UBC67j0f9nktivE | D40: =IFERROR(__xludf.DUMMYFUNCTION("""COMPUTED_VALUE"""),"1TN3z_RT4NXTQfbj6qQEFc9gmXRHLB6-fy_oyWA0RHdU") -> 1TN3z_RT4NXTQfbj6qQEFc9gmXRHLB6-fy_oyWA0RHdU | E40: =IFERROR(__xludf.DUMMYFUNCTION("""COMPUTED_VALUE"""),"1Nn4F-GdSnEftvTXSfmVRSNkPuH0v1E3D") -> 1Nn4F-GdSnEftvTXSfmVRSNkPuH0v1E3D
A41: =IFERROR(__xludf.DUMMYFUNCTION("""COMPUTED_VALUE"""),"122 - Matemática Aplicada 4") -> 122 - Matemática Aplicada 4
A42: =IFERROR(__xludf.DUMMYFUNCTION("""COMPUTED_VALUE"""),"120 - Matemática Aplicada 2") -> 120 - Matemática Aplicada 2
A43: =IFERROR(__xludf.DUMMYFUNCTION("""COMPUTED_VALUE"""),"200 - Ingeniería Eléctrica 1") -> 200 - Ingeniería Eléctrica 1
A44: =IFERROR(__xludf.DUMMYFUNCTION("""COMPUTED_VALUE"""),"724 - Teoría de Sistemas 2") -> 724 - Teoría de Sistemas 2 | B44: =IFERROR(__xludf.DUMMYFUNCTION("""COMPUTED_VALUE"""),"1Oh-yJJ9oc8SdDPJao-u31YXfwOPrsifu2o1a7Sf2-9k") -> 1Oh-yJJ9oc8SdDPJao-u31YXfwOPrsifu2o1a7Sf2-9k | C44: =IFERROR(__xludf.DUMMYFUNCTION("""COMPUTED_VALUE"""),"1O2rxycdV4XrytI_g4llqenReY8-rYp3frKI7rd6fNMI") -> 1O2rxycdV4XrytI_g4llqenReY8-rYp3frKI7rd6fNMI | D44: =IFERROR(__xludf.DUMMYFUNCTION("""COMPUTED_VALUE"""),"1uWuKRV1yUDuRgCMclGBs18DlrkJbY-3RrPrV1PnXLeM") -> 1uWuKRV1yUDuRgCMclGBs18DlrkJbY-3RrPrV1PnXLeM | E44: =IFERROR(__xludf.DUMMYFUNCTION("""COMPUTED_VALUE"""),"1EQVlwt_Q14_MHhr3GeYfJvtnySQAorrC") -> 1EQVlwt_Q14_MHhr3GeYfJvtnySQAorrC
A45: =IFERROR(__xludf.DUMMYFUNCTION("""COMPUTED_VALUE"""),"603 - Investigación de Operaciones 2") -> 603 - Investigación de Operaciones 2
A46: =IFERROR(__xludf.DUMMYFUNCTION("""COMPUTED_VALUE"""),"734 - Estadística 2") -> 734 - Estadística 2
A47: =IFERROR(__xludf.DUMMYFUNCTION("""COMPUTED_VALUE"""),"281 - Sistemas Operativos 1") -> 281 - Sistemas Operativos 1 | B47: =IFERROR(__xludf.DUMMYFUNCTION("""COMPUTED_VALUE"""),"1RAzDRLQZEv8Ck7PxnFQbrklrekiw5bDJFX0wgP7vFSQ") -> 1RAzDRLQZEv8Ck7PxnFQbrklrekiw5bDJFX0wgP7vFSQ | C47: =IFERROR(__xludf.DUMMYFUNCTION("""COMPUTED_VALUE"""),"145JPmfq4pDEEE_ipNtWzYQNDVrAg9WOQ9ocmZu_NegE") -> 145JPmfq4pDEEE_ipNtWzYQNDVrAg9WOQ9ocmZu_NegE | D47: =IFERROR(__xludf.DUMMYFUNCTION("""COMPUTED_VALUE"""),"1HE-c5k7b7a4sV8kZRb8whPINiB0Q_xMq-7-LwYVSiEA") -> 1HE-c5k7b7a4sV8kZRb8whPINiB0Q_xMq-7-LwYVSiEA | E47: =IFERROR(__xludf.DUMMYFUNCTION("""COMPUTED_VALUE"""),"1n0J1NqUgfuTdZBYJs6ClPsEPAT-BsF53") -> 1n0J1NqUgfuTdZBYJs6ClPsEPAT-BsF53
A48: =IFERROR(__xludf.DUMMYFUNCTION("""COMPUTED_VALUE"""),"779 - Arquitectura de Computadoras y Ensambladores 2") -> 779 - Arquitectura de Computadoras y Ensambladores 2 | B48: =IFERROR(__xludf.DUMMYFUNCTION("""COMPUTED_VALUE"""),"1_uxBhWcRvgBlCjf2s6O-Hvly7rBvJyZdswUKwm6KP5Y") -> 1_uxBhWcRvgBlCjf2s6O-Hvly7rBvJyZdswUKwm6KP5Y | C48: =IFERROR(__xludf.DUMMYFUNCTION("""COMPUTED_VALUE"""),"1dqk67SNWBGb15fqe17ZBfmxUg9pla5H7nqVOrGHYEJ4") -> 1dqk67SNWBGb15fqe17ZBfmxUg9pla5H7nqVOrGHYEJ4 | D48: =IFERROR(__xludf.DUMMYFUNCTION("""COMPUTED_VALUE"""),"1I4Bx-1TpNE382Kclmp7qlhsORNllFJ6iza9or1MYlQM") -> 1I4Bx-1TpNE382Kclmp7qlhsORNllFJ6iza9or1MYlQM | E48: =IFERROR(__xludf.DUMMYFUNCTION("""COMPUTED_VALUE"""),"1fb6OBuOK__kn1iOUatpXGXqw-Xx2KUF3") -> 1fb6OBuOK__kn1iOUatpXGXqw-Xx2KUF3
A49: =IFERROR(__xludf.DUMMYFUNCTION("""COMPUTED_VALUE"""),"970 - Redes de Computadoras 1") -> 970 - Redes de Computadoras 1 | B49: =IFERROR(__xludf.DUMMYFUNCTION("""COMPUTED_VALUE"""),"1z_6lSkIcVZpEVQ4tR8c-eSvVvTxWsXwhmFojsLWeBGc") -> 1z_6lSkIcVZpEVQ4tR8c-eSvVvTxWsXwhmFojsLWeBGc | C49: =IFERROR(__xludf.DUMMYFUNCTION("""COMPUTED_VALUE"""),"18wRQLI8Pz51ZFEFWKE1SD6XVhlxOdJa1PpxDFo2dRT4") -> 18wRQLI8Pz51ZFEFWKE1SD6XVhlxOdJa1PpxDFo2dRT4 | D49: =IFERROR(__xludf.DUMMYFUNCTION("""COMPUTED_VALUE"""),"1i-Uona9IG1TfHaWeowvwDDQBbBF5rm-kKLnZwWQbchA") -> 1i-Uona9IG1TfHaWeowvwDDQBbBF5rm-kKLnZwWQbchA | E49: =IFERROR(__xludf.DUMMYFUNCTION("""COMPUTED_VALUE"""),"1MyEh58_aw-4JAg_UmiHarHdZJMAoZYFg") -> 1MyEh58_aw-4JAg_UmiHarHdZJMAoZYFg
A50: =IFERROR(__xludf.DUMMYFUNCTION("""COMPUTED_VALUE"""),"774 - Sistemas de Bases de Datos 1") -> 774 - Sistemas de Bases de Datos 1 | B50: =IFERROR(__xludf.DUMMYFUNCTION("""COMPUTED_VALUE"""),"1h1zzA1-Xq9ihet57bP4f0PLQnKeojJUanhgpuP67hKs") -> 1h1zzA1-Xq9ihet57bP4f0PLQnKeojJUanhgpuP67hKs | C50: =IFERROR(__xludf.DUMMYFUNCTION("""COMPUTED_VALUE"""),"1xYInTWRmhz45q5vjazDVsb1EGOCbYqibWRBgZMK1g2I") -> 1xYInTWRmhz45q5vjazDVsb1EGOCbYqibWRBgZMK1g2I | D50: =IFERROR(__xludf.DUMMYFUNCTION("""COMPUTED_VALUE"""),"1ab_tQ3tdHfx3wTYZggg6topYWfMdNDjc_9Pl6gMgeY0") -> 1ab_tQ3tdHfx3wTYZggg6topYWfMdNDjc_9Pl6gMgeY0 | E50: =IFERROR(__xludf.DUMMYFUNCTION("""COMPUTED_VALUE"""),"1a0bdit9CmOXEhJOXc35cohqfdNKmMAzD") -> 1a0bdit9CmOXEhJOXc35cohqfdNKmMAzD
A51: =IFERROR(__xludf.DUMMYFUNCTION("""COMPUTED_VALUE"""),"2036 - Prácticas Intermedias") -> 2036 - Prácticas Intermedias
A52: =IFERROR(__xludf.DUMMYFUNCTION("""COMPUTED_VALUE"""),"285 - Sistemas Operativos 2") -> 285 - Sistemas Operativos 2 | B52: =IFERROR(__xludf.DUMMYFUNCTION("""COMPUTED_VALUE"""),"1VCx3jdfVNJvtMfY5j_W624CAT1QxC-9qVw_ts_erFM8") -> 1VCx3jdfVNJvtMfY5j_W624CAT1QxC-9qVw_ts_erFM8 | C52: =IFERROR(__xludf.DUMMYFUNCTION("""COMPUTED_VALUE"""),"1ssmi68Gibgtkl07Zn0H_wQWjqhj_SfcpUhCdmyvVjb4") -> 1ssmi68Gibgtkl07Zn0H_wQWjqhj_SfcpUhCdmyvVjb4 | D52: =IFERROR(__xludf.DUMMYFUNCTION("""COMPUTED_VALUE"""),"1bIFK2VHNoCYqh3rnNBIgLzQpv40VUWzyYaRVu-gQbTI") -> 1bIFK2VHNoCYqh3rnNBIgLzQpv40VUWzyYaRVu-gQbTI | E52: =IFERROR(__xludf.DUMMYFUNCTION("""COMPUTED_VALUE"""),"1q8mN6aa9bhjGWUIaszZNHjuEk-b6qckg") -> 1q8mN6aa9bhjGWUIaszZNHjuEk-b6qckg
A53: =IFERROR(__xludf.DUMMYFUNCTION("""COMPUTED_VALUE"""),"975 - Redes de Computadoras 2") -> 975 - Redes de Computadoras 2 | B53: =IFERROR(__xludf.DUMMYFUNCTION("""COMPUTED_VALUE"""),"1JcTacSIMIoXQmOixc1cssvrK_MVzZYH-Yo4FFSny6Nk") -> 1JcTacSIMIoXQmOixc1cssvrK_MVzZYH-Yo4FFSny6Nk | C53: =IFERROR(__xludf.DUMMYFUNCTION("""COMPUTED_VALUE"""),"1JLgRGqqoVVNY2eFrI2m3ylhPGOUPiyZN7_tK8VnOywQ") -> 1JLgRGqqoVVNY2eFrI2m3ylhPGOUPiyZN7_tK8VnOywQ | D53: =IFERROR(__xludf.DUMMYFUNCTION("""COMPUTED_VALUE"""),"1IL8QCca0XDIN9zPNoVS7hKBCHZQ9eh42iA_U0q-_ktQ") -> 1IL8QCca0XDIN9zPNoVS7hKBCHZQ9eh42iA_U0q-_ktQ | E53: =IFERROR(__xludf.DUMMYFUNCTION("""COMPUTED_VALUE"""),"1gu0dvm6zoJE2RmJVBG6ZIV_BFoLoxJfB") -> 1gu0dvm6zoJE2RmJVBG6ZIV_BFoLoxJfB
A54: =IFERROR(__xludf.DUMMYFUNCTION("""COMPUTED_VALUE"""),"775 - Sistemas de Bases de Datos 2") -> 775 - Sistemas de Bases de Datos 2 | B54: =IFERROR(__xludf.DUMMYFUNCTION("""COMPUTED_VALUE"""),"1TCVGX95CGGMGYvyB2K8cDve9RSMthqD6Tc1-CrmctiM") -> 1TCVGX95CGGMGYvyB2K8cDve9RSMthqD6Tc1-CrmctiM | C54: =IFERROR(__xludf.DUMMYFUNCTION("""COMPUTED_VALUE"""),"1c8vA2_5i-ARXIPU3ZxB3bwcKRbWh46erGG5KH3wrJyU") -> 1c8vA2_5i-ARXIPU3ZxB3bwcKRbWh46erGG5KH3wrJyU | D54: =IFERROR(__xludf.DUMMYFUNCTION("""COMPUTED_VALUE"""),"17_WFCeqzOngZrZqB-G0qa2RVksxKYCq8VrQTxvdfvyg") -> 17_WFCeqzOngZrZqB-G0qa2RVksxKYCq8VrQTxvdfvyg | E54: =IFERROR(__xludf.DUMMYFUNCTION("""COMPUTED_VALUE"""),"d/1-KBylfOI9IIiZlF-l2dlJlM6PNNdjzFl") -> d/1-KBylfOI9IIiZlF-l2dlJlM6PNNdjzFl
A55: =IFERROR(__xludf.DUMMYFUNCTION("""COMPUTED_VALUE"""),"283 - Análisis y Diseño de Sistemas 1") -> 283 - Análisis y Diseño de Sistemas 1 | B55: =IFERROR(__xludf.DUMMYFUNCTION("""COMPUTED_VALUE"""),"1Y3HF-OxPbgEhNi6pNhbpImrQsH3btlYO6xtsnryrunY") -> 1Y3HF-OxPbgEhNi6pNhbpImrQsH3btlYO6xtsnryrunY | C55: =IFERROR(__xludf.DUMMYFUNCTION("""COMPUTED_VALUE"""),"12umvxFMZmSLGZenSQOXCnUePgu7-gug8FmFRz5MKlkE") -> 12umvxFMZmSLGZenSQOXCnUePgu7-gug8FmFRz5MKlkE | D55: =IFERROR(__xludf.DUMMYFUNCTION("""COMPUTED_VALUE"""),"1gwmb6_MjiG_JUXAI5JWT33vnYBsnPqtoeHWc1yoFWQQ") -> 1gwmb6_MjiG_JUXAI5JWT33vnYBsnPqtoeHWc1yoFWQQ | E55: =IFERROR(__xludf.DUMMYFUNCTION("""COMPUTED_VALUE"""),"1QXb23bY6W9aTRkpiCON7Q0ews5p7hatK") -> 1QXb23bY6W9aTRkpiCON7Q0ews5p7hatK
A56: =IFERROR(__xludf.DUMMYFUNCTION("""COMPUTED_VALUE"""),"797 - Seminario de Sistemas 1") -> 797 - Seminario de Sistemas 1 | B56: =IFERROR(__xludf.DUMMYFUNCTION("""COMPUTED_VALUE"""),"1VXfuZgL8iNYOe8XfW_5s4rVnIq-_Xurqk8xlOGGexqY") -> 1VXfuZgL8iNYOe8XfW_5s4rVnIq-_Xurqk8xlOGGexqY | C56: =IFERROR(__xludf.DUMMYFUNCTION("""COMPUTED_VALUE"""),"1eWOPuodcZlQ4YNCFI3CQ-Zpw7nxkVx7vi3XlMdj8he4") -> 1eWOPuodcZlQ4YNCFI3CQ-Zpw7nxkVx7vi3XlMdj8he4 | D56: =IFERROR(__xludf.DUMMYFUNCTION("""COMPUTED_VALUE"""),"13DUp9JOUZdD2C1BdD-os-W-bLO-jSufbMHC7eJ5PBSo") -> 13DUp9JOUZdD2C1BdD-os-W-bLO-jSufbMHC7eJ5PBSo | E56: =IFERROR(__xludf.DUMMYFUNCTION("""COMPUTED_VALUE"""),"1EnANLnqSuVktTF4SdlpIOuHPbefsIOnc") -> 1EnANLnqSuVktTF4SdlpIOuHPbefsIOnc
A57: =IFERROR(__xludf.DUMMYFUNCTION("""COMPUTED_VALUE"""),"700 - Ingeniería Económica 1") -> 700 - Ingeniería Económica 1
A58: =IFERROR(__xludf.DUMMYFUNCTION("""COMPUTED_VALUE"""),"729 - Modelación y Simulación 1") -> 729 - Modelación y Simulación 1 | B58: =IFERROR(__xludf.DUMMYFUNCTION("""COMPUTED_VALUE"""),"17u8GNz3HZ-i9KS-yxFiuJx9u7OawTwjyLcvLoG_x6W8") -> 17u8GNz3HZ-i9KS-yxFiuJx9u7OawTwjyLcvLoG_x6W8 | C58: =IFERROR(__xludf.DUMMYFUNCTION("""COMPUTED_VALUE"""),"1NFJSyWLsOrGAG7qFKpXyw79GRTTb4abmj-M6aBddS5U") -> 1NFJSyWLsOrGAG7qFKpXyw79GRTTb4abmj-M6aBddS5U | D58: =IFERROR(__xludf.DUMMYFUNCTION("""COMPUTED_VALUE"""),"1toY-3JEeuVBJwRbyxsqyquwh-orXIfZE8KB3e43PXok") -> 1toY-3JEeuVBJwRbyxsqyquwh-orXIfZE8KB3e43PXok | E58: =IFERROR(__xludf.DUMMYFUNCTION("""COMPUTED_VALUE"""),"15sfPZmXt41hGkttgpVICPuKozdPNEJ6A") -> 15sfPZmXt41hGkttgpVICPuKozdPNEJ6A
A59: =IFERROR(__xludf.DUMMYFUNCTION("""COMPUTED_VALUE"""),"786 - Sistemas Organizacionales y Gerenciales 1") -> 786 - Sistemas Organizacionales y Gerenciales 1 | B59: =IFERROR(__xludf.DUMMYFUNCTION("""COMPUTED_VALUE"""),"1VTtCckO64u9REDx8UoxNJrYiavZGQU_hh4HvsOUiqlc") -> 1VTtCckO64u9REDx8UoxNJrYiavZGQU_hh4HvsOUiqlc | C59: =IFERROR(__xludf.DUMMYFUNCTION("""COMPUTED_VALUE"""),"1dMwVEKpg3j4uCN3CqoVXOWkBQbHNw7DIhtU8Bhc5Mqc") -> 1dMwVEKpg3j4uCN3CqoVXOWkBQbHNw7DIhtU8Bhc5Mqc | D59: =IFERROR(__xludf.DUMMYFUNCTION("""COMPUTED_VALUE"""),"1eh447vkO2YeAmVFqKtzinqlk4a4Y1JJKjOtv9eVOlY0") -> 1eh447vkO2YeAmVFqKtzinqlk4a4Y1JJKjOtv9eVOlY0 | E59: =IFERROR(__xludf.DUMMYFUNCTION("""COMPUTED_VALUE"""),"1txIe6LugQ0CGgSIkqRY1UZvHL7CtMqgD") -> 1txIe6LugQ0CGgSIkqRY1UZvHL7CtMqgD
A60: =IFERROR(__xludf.DUMMYFUNCTION("""COMPUTED_VALUE"""),"972 - Inteligencia Artificial 1") -> 972 - Inteligencia Artificial 1 | B60: =IFERROR(__xludf.DUMMYFUNCTION("""COMPUTED_VALUE"""),"1C04a6qH3d2zJVb1hJwa6tsRQVM9LUb_nwyxMovG5tdI") -> 1C04a6qH3d2zJVb1hJwa6tsRQVM9LUb_nwyxMovG5tdI | C60: =IFERROR(__xludf.DUMMYFUNCTION("""COMPUTED_VALUE"""),"1CEh1GcUg3ntzgPT9yUocLDlrLJKmZCCl1MWUrEyfwzg") -> 1CEh1GcUg3ntzgPT9yUocLDlrLJKmZCCl1MWUrEyfwzg | D60: =IFERROR(__xludf.DUMMYFUNCTION("""COMPUTED_VALUE"""),"1oncZrzGawvfNWTdhWsLhXGKvrApliYXhCf81eUnkV20") -> 1oncZrzGawvfNWTdhWsLhXGKvrApliYXhCf81eUnkV20 | E60: =IFERROR(__xludf.DUMMYFUNCTION("""COMPUTED_VALUE"""),"1eMKEvvWQ4yFq38z3ks0ZmIZ43xAVGgyM") -> 1eMKEvvWQ4yFq38z3ks0ZmIZ43xAVGgyM
A61: =IFERROR(__xludf.DUMMYFUNCTION("""COMPUTED_VALUE"""),"966 - Seguridad y Auditoría de Redes de Computadoras") -> 966 - Seguridad y Auditoría de Redes de Computadoras
A62: =IFERROR(__xludf.DUMMYFUNCTION("""COMPUTED_VALUE"""),"785 - Análisis y Diseño de Sistemas 2") -> 785 - Análisis y Diseño de Sistemas 2 | B62: =IFERROR(__xludf.DUMMYFUNCTION("""COMPUTED_VALUE"""),"1_ufF1kvClwUUTsCz0V0fLuXjs_JRZWRSMCWkUEd8co4") -> 1_ufF1kvClwUUTsCz0V0fLuXjs_JRZWRSMCWkUEd8co4 | C62: =IFERROR(__xludf.DUMMYFUNCTION("""COMPUTED_VALUE"""),"1HaBdPkxZx1GRiw5WlqxQhbxPWuW-mZVFEoUho7tsLDY") -> 1HaBdPkxZx1GRiw5WlqxQhbxPWuW-mZVFEoUho7tsLDY
A63: =IFERROR(__xludf.DUMMYFUNCTION("""COMPUTED_VALUE"""),"798 - Seminario de Sistemas 2") -> 798 - Seminario de Sistemas 2 | B63: =IFERROR(__xludf.DUMMYFUNCTION("""COMPUTED_VALUE"""),"1v6hbJdWzxkj7s5D7oM894pu3kMAvhEZGXUMfRFv7yKQ") -> 1v6hbJdWzxkj7s5D7oM894pu3kMAvhEZGXUMfRFv7yKQ | C63: =IFERROR(__xludf.DUMMYFUNCTION("""COMPUTED_VALUE"""),"1LxPO_wuZRiAXrS1EicVG-gQWzjILKll8Nqvs3MS7G_k") -> 1LxPO_wuZRiAXrS1EicVG-gQWzjILKll8Nqvs3MS7G_k | D63: =IFERROR(__xludf.DUMMYFUNCTION("""COMPUTED_VALUE"""),"1BWLmO3asfl7g244aKrskvOVVUItkuDglmE1c2bmkR30") -> 1BWLmO3asfl7g244aKrskvOVVUItkuDglmE1c2bmkR30 | E63: =IFERROR(__xludf.DUMMYFUNCTION("""COMPUTED_VALUE"""),"1Aq8boJeyyodIKEdkrfe9fWB5RIGSLDb5") -> 1Aq8boJeyyodIKEdkrfe9fWB5RIGSLDb5
A64: =IFERROR(__xludf.DUMMYFUNCTION("""COMPUTED_VALUE"""),"788 - Sistemas Aplicados 1") -> 788 - Sistemas Aplicados 1
A65: =IFERROR(__xludf.DUMMYFUNCTION("""COMPUTED_VALUE"""),"776 - Bases de Datos Avanzadas") -> 776 - Bases de Datos Avanzadas | B65: =IFERROR(__xludf.DUMMYFUNCTION("""COMPUTED_VALUE"""),"1SZ2dJz29IsruB5vMYQ514xwGe6wyVx6cjMu_iwnHpFo") -> 1SZ2dJz29IsruB5vMYQ514xwGe6wyVx6cjMu_iwnHpFo
A66: =IFERROR(__xludf.DUMMYFUNCTION("""COMPUTED_VALUE"""),"2009 - Prácticas Finales Ingeniería Ciencias y Sistemas") -> 2009 - Prácticas Finales Ingeniería Ciencias y Sistemas
A67: =IFERROR(__xludf.DUMMYFUNCTION("""COMPUTED_VALUE"""),"720 - Modelación y Simulación 2") -> 720 - Modelación y Simulación 2 | B67: =IFERROR(__xludf.DUMMYFUNCTION("""COMPUTED_VALUE"""),"1ebc3-I4AbsLDHtzhtolQz7pqZDPvmSE0yZJu1xY6lLY") -> 1ebc3-I4AbsLDHtzhtolQz7pqZDPvmSE0yZJu1xY6lLY | C67: =IFERROR(__xludf.DUMMYFUNCTION("""COMPUTED_VALUE"""),"1VnSdYE6hCH1oAG4XdaAltDp-IuIjLZzv9KdrOGh2-0Y") -> 1VnSdYE6hCH1oAG4XdaAltDp-IuIjLZzv9KdrOGh2-0Y | D67: =IFERROR(__xludf.DUMMYFUNCTION("""COMPUTED_VALUE"""),"1LLT4wjh6eEkdi7y6_yd99pbR2Q8NPBHYmsciMZpRqUE") -> 1LLT4wjh6eEkdi7y6_yd99pbR2Q8NPBHYmsciMZpRqUE | E67: =IFERROR(__xludf.DUMMYFUNCTION("""COMPUTED_VALUE"""),"11D7BpB1NYAQLsl-xomWKo7ibetJ_b2JE") -> 11D7BpB1NYAQLsl-xomWKo7ibetJ_b2JE
A68: =IFERROR(__xludf.DUMMYFUNCTION("""COMPUTED_VALUE"""),"787 - Sistemas Organizacionales y Gerenciales 2") -> 787 - Sistemas Organizacionales y Gerenciales 2 | B68: =IFERROR(__xludf.DUMMYFUNCTION("""COMPUTED_VALUE"""),"1KpYHYX_EAJ-h4GLtSoCT8Rqz-xU4Qh5pUnEiPyxmEZA") -> 1KpYHYX_EAJ-h4GLtSoCT8Rqz-xU4Qh5pUnEiPyxmEZA | C68: =IFERROR(__xludf.DUMMYFUNCTION("""COMPUTED_VALUE"""),"106SYnPHxQ47_qT62NOXndjd6mPwE7LV7AXR9D4-euB8") -> 106SYnPHxQ47_qT62NOXndjd6mPwE7LV7AXR9D4-euB8 | D68: =IFERROR(__xludf.DUMMYFUNCTION("""COMPUTED_VALUE"""),"1uo3-u0rbLWUGIyMydUz-lOWpj7xdx2oKwNH9T1cU12A") -> 1uo3-u0rbLWUGIyMydUz-lOWpj7xdx2oKwNH9T1cU12A | E68: =IFERROR(__xludf.DUMMYFUNCTION("""COMPUTED_VALUE"""),"1wmyYrKnHpQJd0Iebc9cCHZwq93Te5Iq8") -> 1wmyYrKnHpQJd0Iebc9cCHZwq93Te5Iq8
A69: =IFERROR(__xludf.DUMMYFUNCTION("""COMPUTED_VALUE"""),"790 - Emprendedores de Negocios Informáticos") -> 790 - Emprendedores de Negocios Informáticos
A70: =IFERROR(__xludf.DUMMYFUNCTION("""COMPUTED_VALUE"""),"968 - Inteligencia Artificial 2") -> 968 - Inteligencia Artificial 2
A71: =IFERROR(__xludf.DUMMYFUNCTION("""COMPUTED_VALUE"""),"974 - Redes de Nueva Generación") -> 974 - Redes de Nueva Generación
A72: =IFERROR(__xludf.DUMMYFUNCTION("""COMPUTED_VALUE"""),"780 - Software Avanzado") -> 780 - Software Avanzado | B72: =IFERROR(__xludf.DUMMYFUNCTION("""COMPUTED_VALUE"""),"1SZ2dJz29IsruB5vMYQ514xwGe6wyVx6cjMu_iwnHpFo") -> 1SZ2dJz29IsruB5vMYQ514xwGe6wyVx6cjMu_iwnHpFo | C72: =IFERROR(__xludf.DUMMYFUNCTION("""COMPUTED_VALUE"""),"13JrqVT0c3I6SzCOF1sKpi1qJKOryNTT4TsCaNwuV-24") -> 13JrqVT0c3I6SzCOF1sKpi1qJKOryNTT4TsCaNwuV-24 | D72: =IFERROR(__xludf.DUMMYFUNCTION("""COMPUTED_VALUE"""),"1QVpX8zi83Rr6KfcUvSEKp9NqRCfEFmL1eZ88Oeeolto") -> 1QVpX8zi83Rr6KfcUvSEKp9NqRCfEFmL1eZ88Oeeolto | E72: =IFERROR(__xludf.DUMMYFUNCTION("""COMPUTED_VALUE"""),"1j6tUIPNPfK0lVrpQxNZKyB23LcXzn5Ge") -> 1j6tUIPNPfK0lVrpQxNZKyB23LcXzn5Ge
A73: =IFERROR(__xludf.DUMMYFUNCTION("""COMPUTED_VALUE"""),"789 - Sistemas Aplicados 2") -> 789 - Sistemas Aplicados 2
A74: =IFERROR(__xludf.DUMMYFUNCTION("""COMPUTED_VALUE"""),"735 - Auditoría de Proyectos de Software") -> 735 - Auditoría de Proyectos de Software
A75: =IFERROR(__xludf.DUMMYFUNCTION("""COMPUTED_VALUE"""),"7999 - Seminario de Investigación EPS Sistemas") -> 7999 - Seminario de Investigación EPS Sistemas
A76: =IFERROR(__xludf.DUMMYFUNCTION("""COMPUTED_VALUE"""),"799 - Seminario de Investigación") -> 799 - Seminario de Investigación
A77: =IFERROR(__xludf.DUMMYFUNCTION("""COMPUTED_VALUE"""),"90 - Programacion de Computadoras 1") -> 90 - Programacion de Computadoras 1 | B77: =IFERROR(__xludf.DUMMYFUNCTION("""COMPUTED_VALUE"""),"1qvDDGj5yCc7f5CzNszeAsW2HPXfptQjvWIcbjskCMYM") -> 1qvDDGj5yCc7f5CzNszeAsW2HPXfptQjvWIcbjskCMYM | C77: =IFERROR(__xludf.DUMMYFUNCTION("""COMPUTED_VALUE"""),"1YPGQg3r0TE0ZsibgKarHMDVR2FLaHLC0G5O84_GpNhw") -> 1YPGQg3r0TE0ZsibgKarHMDVR2FLaHLC0G5O84_GpNhw | D77: =IFERROR(__xludf.DUMMYFUNCTION("""COMPUTED_VALUE"""),"1A_jprbCHQlF7SUg-tly0Ak7hJtMh8U9qL3lUg0S2T4U") -> 1A_jprbCHQlF7SUg-tly0Ak7hJtMh8U9qL3lUg0S2T4U | E77: =IFERROR(__xludf.DUMMYFUNCTION("""COMPUTED_VALUE"""),"1QT0XgtJhS0WdXvrmJ9l5fhkQxyPS7eMI") -> 1QT0XgtJhS0WdXvrmJ9l5fhkQxyPS7eMI
A78: =IFERROR(__xludf.DUMMYFUNCTION("""COMPUTED_VALUE"""),"92 - Programacion de Computadoras 2") -> 92 - Programacion de Computadoras 2 | B78: =IFERROR(__xludf.DUMMYFUNCTION("""COMPUTED_VALUE"""),"1SCiXODhHsEGBVGnnYk9ZrO_gSOSvcGwu7lDEJBfLaEw") -> 1SCiXODhHsEGBVGnnYk9ZrO_gSOSvcGwu7lDEJBfLaEw | C78: =IFERROR(__xludf.DUMMYFUNCTION("""COMPUTED_VALUE"""),"1Bf3nWt47xcnM3VU3BvJaD4AcWQd-1GK4pJm4b69PzDk") -> 1Bf3nWt47xcnM3VU3BvJaD4AcWQd-1GK4pJm4b69PzDk | D78: =IFERROR(__xludf.DUMMYFUNCTION("""COMPUTED_VALUE"""),"1DHgSe2VDZ9KBUhl4_7NdyzagI7iar5NJSgD9rUtytdY") -> 1DHgSe2VDZ9KBUhl4_7NdyzagI7iar5NJSgD9rUtytdY | E78: =IFERROR(__xludf.DUMMYFUNCTION("""COMPUTED_VALUE"""),"1FHqe10A7z4kQFMWfvfI8tkxBkAgiF7u2e1XlqT1-63E") -> 1FHqe10A7z4kQFMWfvfI8tkxBkAgiF7u2e1XlqT1-63E
A79: =IFERROR(__xludf.DUMMYFUNCTION("""COMPUTED_VALUE"""),"667 - Programacion Comercial 1") -> 667 - Programacion Comercial 1 | B79: =IFERROR(__xludf.DUMMYFUNCTION("""COMPUTED_VALUE"""),"1q-0CM7N_hXOxknvTAL7P8U9-t9hqpm1-3l5E6r3G-qg") -> 1q-0CM7N_hXOxknvTAL7P8U9-t9hqpm1-3l5E6r3G-qg | C79: =IFERROR(__xludf.DUMMYFUNCTION("""COMPUTED_VALUE"""),"1R41rwbBQZrh9qjZ3XYjH5mTM9rwh34s58Htn787_YnY") -> 1R41rwbBQZrh9qjZ3XYjH5mTM9rwh34s58Htn787_YnY | D79: =IFERROR(__xludf.DUMMYFUNCTION("""COMPUTED_VALUE"""),"1s3J2CHGyPGSPwPm7T7m5o_7sQCrWwpQ5xqzAk04bgVA") -> 1s3J2CHGyPGSPwPm7T7m5o_7sQCrWwpQ5xqzAk04bgVA | E79: =IFERROR(__xludf.DUMMYFUNCTION("""COMPUTED_VALUE"""),"1VSynsMtKbK1ktIqRzKf6QEpnepidsJka") -> 1VSynsMtKbK1ktIqRzKf6QEpnepidsJka
A80: =IFERROR(__xludf.DUMMYFUNCTION("""COMPUTED_VALUE"""),"768 - Algoritmos") -> 768 - Algoritmos | B80: =IFERROR(__xludf.DUMMYFUNCTION("""COMPUTED_VALUE"""),"1SjAd6zUsLAnVyCAYH7AjoRBdaM836qJGVSbcpa5npcA") -> 1SjAd6zUsLAnVyCAYH7AjoRBdaM836qJGVSbcpa5npcA | C80: =IFERROR(__xludf.DUMMYFUNCTION("""COMPUTED_VALUE"""),"1afm0IKlaJOgHVN4bCH6AUAoNUqhq0_44_T5aENeyCWo") -> 1afm0IKlaJOgHVN4bCH6AUAoNUqhq0_44_T5aENeyCWo | D80: =IFERROR(__xludf.DUMMYFUNCTION("""COMPUTED_VALUE"""),"1G1fW33CrLmmI1Pxdgw_cAdUJKRHg8LpG4-p2vnoWUqw") -> 1G1fW33CrLmmI1Pxdgw_cAdUJKRHg8LpG4-p2vnoWUqw | E80: =IFERROR(__xludf.DUMMYFUNCTION("""COMPUTED_VALUE"""),"1ySU7wJA5-EonRSWzEsgL03LPoX0Yz7rw") -> 1ySU7wJA5-EonRSWzEsgL03LPoX0Yz7rw
A81: =IFERROR(__xludf.DUMMYFUNCTION("""COMPUTED_VALUE"""),"0089 - Comunicación Asertiva") -> 0089 - Comunicación Asertiva | D81: =IFERROR(__xludf.DUMMYFUNCTION("""COMPUTED_VALUE"""),"1_Ei-qZBLFjKXYNiETo-SLQ_i6LLtwBqz0DelGIPi31I") -> 1_Ei-qZBLFjKXYNiETo-SLQ_i6LLtwBqz0DelGIPi31I | E81: =IFERROR(__xludf.DUMMYFUNCTION("""COMPUTED_VALUE"""),"10NGlQjOf6PbS47vS9QrPsz0UIEnfLTPH") -> 10NGlQjOf6PbS47vS9QrPsz0UIEnfLTPH
